Workbook

Sheet Resumen
B1: Frilo · URLs finales del sitio, metadatos, datos estructurados y keyword objetivo
B2: Versión del 20 de octubre de 2026. Fuente: wireframes aprobados (lienzo "Frilo — Sitio web"), Especificacion_SEO_sitio_Frilo_v2.md y Keyword research Frilo (v3), exports de Semrush del 16 y 19 de octubre de 2026, base Colombia.
B3: Decisión de URL para la app web
B4: Recomendación: el sitio de contenido ocupa https://frilo.dev y la app pasa a https://app.frilo.dev, con noindex, nofollow y fuera del sitemap. Detalle, alternativa y pasos de migración en la hoja "App y ambientes".
B5: Hojas
B6: URLs: inventario de todas las direcciones con estado, indexación, keyword objetivo, title, meta description, H1, tipo de schema y notas. Las longitudes de title y meta se calculan con fórmula y se marcan en rojo si salen del rango.
B7: Datos estructurados: el JSON-LD completo de cada URL (un solo @graph por página) con las preguntas frecuentes visibles en los wireframes. Copiar tal cual en el código.
B8: Keywords: las 106 keywords del research con su página, rol, volumen y KD. Alimenta los volúmenes de la hoja URLs y del forecast.
B9: Forecast base: clics mensuales estimados por URL en posición 10, 3 y 1, con las CTR de la hoja Supuestos. Es un techo: no descuenta AI Overviews, anuncios ni el conversor de Google.
B10: Seguimiento: hoja para llenar con datos de Search Console, Ranki y PageSpeed (indexación, posición, clics, Core Web Vitals).
B11: App y ambientes: dónde vive la app, ambiente de prueba, publicación manual, redirecciones y archivos técnicos.
B12: Cómo se eligió la keyword objetivo
... B17: Medir en Ranki las keywords sin volumen: frilo, calculadoras para independientes, guías para independientes, cesantías para independientes, dónde guardar las cesantías, qué hacer con las cesantías, glosario seguridad social, recibir dólares en colombia. Diseñar /glosario, /quienes-somos, /metodologia y /transparencia. Confirmar las rutas actuales de Términos y Política de datos en la app.

Sheet URLs
A1: ID | B1: Página | C1: URL final | D1: Ruta | E1: Tipo | F1: Wireframe | G1: Estado | H1: Meta robots | I1: En sitemap | J1: Canonical | K1: Prioridad | L1: Keyword objetivo | M1: Coincidencia con el H1 | N1: Volumen keyword objetivo | O1: KD | P1: Volumen del grupo (principal + secundarias + soporte) | Q1: Keywords secundarias | R1: Title | S1: Long. title | T1: Meta description | U1: Long. meta | V1: H1 | W1: og:type | X1: Datos estructurados | Y1: Breadcrumb | Z1: Frecuencia de actualización | AA1: Notas
A2: Home | B2: Inicio | C2: https://frilo.dev/ | D2: / | E2: Home | F2: Main.dc.html | G2: Wireframe aprobado | H2: index, follow | I2: Sí | J2: https://frilo.dev/ | K2: 1 - Alta | L2: frilo | M2: Exacta (H1 = "Frilo") | N2: =IFERROR(INDEX(Keywords!$F$2:$F$107,MATCH(L2,Keywords!$A$2:$A$107,0)),"s/d") -> s/d | O2: =IFERROR(IF(INDEX(Keywords!$G$2:$G$107,MATCH(L2,Keywords!$A$2:$A$107,0))="","s/d",INDEX(Keywords!$G$2:$G$107,MATCH(L2,Keywords!$A$2:$A$107,0))),"s/d") -> s/d | P2: =SUMIFS(Keywords!$F$2:$F$107,Keywords!$C$2:$C$107,A2,Keywords!$D$2:$D$107,"Principal")+SUMIFS(Keywords!$F$2:$F$107,Keywords!$C$2:$C$107,A2,Keywords!$D$2:$D$107,"Secundaria")+SUMIFS(Keywords!$F$2:$F$107,Keywords!$C$2:$C$107,A2,Keywords!$D$2:$D$107,"Soporte (H2/FAQ)") -> 0 | Q2: calculadoras para independientes (H2, sin datos); app para independientes (sin datos) | R2: Frilo: calculadoras de aportes y cesantías para independientes | S2: =LEN(R2) -> 62 | T2: Calcula tu planilla de independiente, aparta tu prima y tus cesantías y sigue el dólar. Gratis, en pesos o en dólares, sin registro. | U2: =IF(LEFT(T2,1)="(","",LEN(T2)) -> 132 | V2: Frilo | W2: website | X2: Organization + WebSite + Person + WebPage + FAQPage | Y2: — | Z2: Mensual | AA2: Compite por marca. El title empieza con la marca, por eso no lleva sufijo. La demanda no de marca llega por los enlaces a P01, P03 y P10. Medir "frilo" y "app para independientes" en Ranki.
A3: Hub-C | B3: Hub de calculadoras | C3: https://frilo.dev/calculadoras | D3: /calculadoras | E3: Hub | F3: CalculadorasHub.dc.html | G3: Wireframe aprobado | H3: index, follow | I3: Sí | J3: https://frilo.dev/calculadoras | K3: 2 - Media | L3: calculadoras para independientes | M3: Exacta | N3: =IFERROR(INDEX(Keywords!$F$2:$F$107,MATCH(L3,Keywords!$A$2:$A$107,0)),"s/d") -> s/d | O3: =IFERROR(IF(INDEX(Keywords!$G$2:$G$107,MATCH(L3,Keywords!$A$2:$A$107,0))="","s/d",INDEX(Keywords!$G$2:$G$107,MATCH(L3,Keywords!$A$2:$A$107,0))),"s/d") -> s/d | P3: =SUMIFS(Keywords!$F$2:$F$107,Keywords!$C$2:$C$107,A3,Keywords!$D$2:$D$107,"Principal")+SUMIFS(Keywords!$F$2:$F$107,Keywords!$C$2:$C$107,A3,Keywords!$D$2:$D$107,"Secundaria")+SUMIFS(Keywords!$F$2:$F$107,Keywords!$C$2:$C$107,A3,Keywords!$D$2:$D$107,"Soporte (H2/FAQ)") -> 0 | Q3: calculadoras para contratistas (sin datos) | R3: Calculadoras para independientes y contratistas | Frilo | S3: =LEN(R3) -> 55 | T3: Calculadoras gratis para independientes en Colombia: aportes, fecha de pago de la planilla, cesantías e intereses y dólar hoy. Sin registro. | U3: =IF(LEFT(T3,1)="(","",LEN(T3)) -> 140 | V3: Calculadoras para independientes y contratistas en Colombia | W3: website | X3: CollectionPage + ItemList + BreadcrumbList | Y3: Inicio › Calculadoras | Z3: Cuando se agregue una calculadora | AA3: Keyword sin volumen medido: incluirla en Ranki. Su rol principal es repartir autoridad a P01, P03, P05 y P10.
A4: P01 | B4: Calculadora de aportes | C4: https://frilo.dev/calculadoras/aportes-independientes | D4: /calculadoras/aportes-independientes | E4: Herramienta | F4: Calculadora.dc.html | G4: Wireframe aprobado | H4: index, follow | I4: Sí | J4: https://frilo.dev/calculadoras/aportes-independientes | K4: 1 - Alta | L4: calculadora de aportes | M4: Exacta | N4: =IFERROR(INDEX(Keywords!$F$2:$F$107,MATCH(L4,Keywords!$A$2:$A$107,0)),"s/d") -> 2400 | O4: =IFERROR(IF(INDEX(Keywords!$G$2:$G$107,MATCH(L4,Keywords!$A$2:$A$107,0))="","s/d",INDEX(Keywords!$G$2:$G$107,MATCH(L4,Keywords!$A$2:$A$107,0))),"s/d") -> 0 | P4: =SUMIFS(Keywords!$F$2:$F$107,Keywords!$C$2:$C$107,A4,Keywords!$D$2:$D$107,"Principal")+SUMIFS(Keywords!$F$2:$F$107,Keywords!$C$2:$C$107,A4,Keywords!$D$2:$D$107,"Secundaria")+SUMIFS(Keywords!$F$2:$F$107,Keywords!$C$2:$C$107,A4,Keywords!$D$2:$D$107,"Soporte (H2/FAQ)") -> 2580 | Q4: calculadora de aportes para independientes y contratistas; calculadora de aportes 2026; calculadora de liquidacion aportes en linea | R4: Calculadora de aportes para independientes 2026 | Frilo | S4: =LEN(R4) -> 55 | T4: Calcula cuánto pagas de salud, pensión, ARL y Fondo de Solidaridad como independiente o contratista en 2026. Gratis y sin registro. | U4: =IF(LEFT(T4,1)="(","",LEN(T4)) -> 131 | V4: Calculadora de aportes para independientes 2026 | W4: website | X4: WebPage + WebApplication + FAQPage + BreadcrumbList | Y4: Inicio › Calculadoras › Aportes para independientes | Z4: Anual (1.ª quincena de diciembre) y cuando cambie una norma | AA4: Pico de enero (4.400 búsquedas vs. 1.600 en meses bajos). Actualizar año y cifras antes del 15 de diciembre.
A5: P02 | B5: Guía del IBC | C5: https://frilo.dev/guias/ibc-independientes | D5: /guias/ibc-independientes | E5: Guía | F5: GuiaIBC.dc.html | G5: Wireframe aprobado | H5: index, follow | I5: Sí | J5: https://frilo.dev/guias/ibc-independientes | K5: 2 - Media | L5: ibc para independientes | M5: Exacta | N5: =IFERROR(INDEX(Keywords!$F$2:$F$107,MATCH(L5,Keywords!$A$2:$A$107,0)),"s/d") -> 90 | O5: =IFERROR(IF(INDEX(Keywords!$G$2:$G$107,MATCH(L5,Keywords!$A$2:$A$107,0))="","s/d",INDEX(Keywords!$G$2:$G$107,MATCH(L5,Keywords!$A$2:$A$107,0))),"s/d") -> 0 | P5: =SUMIFS(Keywords!$F$2:$F$107,Keywords!$C$2:$C$107,A5,Keywords!$D$2:$D$107,"Principal")+SUMIFS(Keywords!$F$2:$F$107,Keywords!$C$2:$C$107,A5,Keywords!$D$2:$D$107,"Secundaria")+SUMIFS(Keywords!$F$2:$F$107,Keywords!$C$2:$C$107,A5,Keywords!$D$2:$D$107,"Soporte (H2/FAQ)") -> 340 | Q5: calculadora ibc independientes (110, H2); como calcular el ibc para independientes 2026; como cambiar el ibc en soi para independientes | R5: IBC para independientes 2026: qué es y cómo calcularlo | Frilo | S5: =LEN(R5) -> 62 | T5: Qué es el IBC de un independiente, cómo calcularlo en 2026 con el 40% de tus ingresos y cómo cambiarlo en SOI. Con calculadora gratis. | U5: =IF(LEFT(T5,1)="(","",LEN(T5)) -> 134 | V5: IBC para independientes 2026: qué es y cómo calcularlo | W5: article | X5: Article + FAQPage + BreadcrumbList | Y5: Inicio › Guías › IBC para independientes | Z5: Anual (diciembre) | AA5: "calculadora ibc independientes" tiene más volumen (110) pero se queda como secundaria para no competir con P01, que ya calcula el IBC.
A6: P03 | B6: Calculadora de cesantías | C6: https://frilo.dev/calculadoras/cesantias | D6: /calculadoras/cesantias | E6: Herramienta | F6: Cesantias.dc.html | G6: Wireframe aprobado | H6: index, follow | I6: Sí | J6: https://frilo.dev/calculadoras/cesantias | K6: 1 - Alta | L6: calculadora de intereses de cesantías | M6: Parcial: el H1 dice "Calculadora de cesantías e intereses de cesantías" | N6: =IFERROR(INDEX(Keywords!$F$2:$F$107,MATCH(L6,Keywords!$A$2:$A$107,0)),"s/d") -> 880 | O6: =IFERROR(IF(INDEX(Keywords!$G$2:$G$107,MATCH(L6,Keywords!$A$2:$A$107,0))="","s/d",INDEX(Keywords!$G$2:$G$107,MATCH(L6,Keywords!$A$2:$A$107,0))),"s/d") -> 0 | P6: =SUMIFS(Keywords!$F$2:$F$107,Keywords!$C$2:$C$107,A6,Keywords!$D$2:$D$107,"Principal")+SUMIFS(Keywords!$F$2:$F$107,Keywords!$C$2:$C$107,A6,Keywords!$D$2:$D$107,"Secundaria")+SUMIFS(Keywords!$F$2:$F$107,Keywords!$C$2:$C$107,A6,Keywords!$D$2:$D$107,"Soporte (H2/FAQ)") -> 1130 | Q6: intereses de cesantías 2026 calculadora; calculadora de cesantías 2026; calculadora de cesantías e intereses | R6: Calculadora de cesantías e intereses de cesantías 2026 | Frilo | S6: =LEN(R6) -> 62 | T6: Calcula tus cesantías y los intereses del 12% en 2026, con contrato laboral o como independiente. Incluye años anteriores. Sin registro. | U6: =IF(LEFT(T6,1)="(","",LEN(T6)) -> 136 | V6: Calculadora de cesantías e intereses de cesantías 2026 | W6: website | X6: WebPage + WebApplication + FAQPage + BreadcrumbList | Y6: Inicio › Calculadoras › Cesantías e intereses | Z6: Anual (diciembre) | AA6: El H1 cubre "calculadora de cesantías" e "intereses de cesantías" por separado. Se mantiene: Google trata ambas formas como la misma intención y el H1 suena natural. Usar la frase exacta en el primer párrafo.
A7: P04 | B7: Descargar planilla | C7: https://frilo.dev/guias/descargar-planilla-seguridad-social | D7: /guias/descargar-planilla-seguridad-social | E7: Guía | F7: GuiaDescargarPlanilla.dc.html | G7: Wireframe aprobado | H7: index, follow | I7: Sí | J7: https://frilo.dev/guias/descargar-planilla-seguridad-social | K7: 1 - Alta | L7: descargar planilla de seguridad social | M7: Parcial: el H1 dice "Cómo descargar y verificar tu planilla de seguridad social" | N7: =IFERROR(INDEX(Keywords!$F$2:$F$107,MATCH(L7,Keywords!$A$2:$A$107,0)),"s/d") -> 1300 | O7: =IFERROR(IF(INDEX(Keywords!$G$2:$G$107,MATCH(L7,Keywords!$A$2:$A$107,0))="","s/d",INDEX(Keywords!$G$2:$G$107,MATCH(L7,Keywords!$A$2:$A$107,0))),"s/d") -> 0 | P7: =SUMIFS(Keywords!$F$2:$F$107,Keywords!$C$2:$C$107,A7,Keywords!$D$2:$D$107,"Principal")+SUMIFS(Keywords!$F$2:$F$107,Keywords!$C$2:$C$107,A7,Keywords!$D$2:$D$107,"Secundaria")+SUMIFS(Keywords!$F$2:$F$107,Keywords!$C$2:$C$107,A7,Keywords!$D$2:$D$107,"Soporte (H2/FAQ)") -> 2110 | Q7: como descargar planilla de seguridad social (390); como verificar una planilla de seguridad social (210); planilla de seguridad social independiente (210) | R7: Descargar planilla de seguridad social: paso a paso | Frilo | S7: =LEN(R7) -> 59 | T7: Descarga tu planilla de seguridad social, verifica que el pago quedó registrado y conoce qué cambia si eres independiente. Guía 2026. | U7: =IF(LEFT(T7,1)="(","",LEN(T7)) -> 133 | V7: Cómo descargar y verificar tu planilla de seguridad social | W7: article | X7: Article + FAQPage + BreadcrumbList | Y7: Inicio › Guías › Descargar la planilla | Z7: Semestral (revisar enlaces de operadores) | AA7: El title lleva la frase exacta y el H1 suma la variante "verificar" (210). Grupo informativo con mejor relación volumen/dificultad.
A8: P05 | B8: Fecha de pago de la planilla | C8: https://frilo.dev/calculadoras/fecha-pago-planilla | D8: /calculadoras/fecha-pago-planilla | E8: Herramienta | F8: FechaPago.dc.html | G8: Wireframe aprobado | H8: index, follow | I8: Sí | J8: https://frilo.dev/calculadoras/fecha-pago-planilla | K8: 2 - Media | L8: fecha de pago planilla seguridad social | M8: Parcial: el H1 dice "Fechas de pago de la planilla de seguridad social 2026" | N8: =IFERROR(INDEX(Keywords!$F$2:$F$107,MATCH(L8,Keywords!$A$2:$A$107,0)),"s/d") -> 320 | O8: =IFERROR(IF(INDEX(Keywords!$G$2:$G$107,MATCH(L8,Keywords!$A$2:$A$107,0))="","s/d",INDEX(Keywords!$G$2:$G$107,MATCH(L8,Keywords!$A$2:$A$107,0))),"s/d") -> 0 | P8: =SUMIFS(Keywords!$F$2:$F$107,Keywords!$C$2:$C$107,A8,Keywords!$D$2:$D$107,"Principal")+SUMIFS(Keywords!$F$2:$F$107,Keywords!$C$2:$C$107,A8,Keywords!$D$2:$D$107,"Secundaria")+SUMIFS(Keywords!$F$2:$F$107,Keywords!$C$2:$C$107,A8,Keywords!$D$2:$D$107,"Soporte (H2/FAQ)") -> 320 | Q8: — | R8: Fechas de pago de la planilla de seguridad social 2026 | Frilo | S8: =LEN(R8) -> 62 | T8: Consulta la fecha límite para pagar la planilla de seguridad social en 2026 según los últimos dígitos de tu documento. Calendario completo. | U8: =IF(LEFT(T8,1)="(","",LEN(T8)) -> 139 | V8: Fechas de pago de la planilla de seguridad social 2026 | W8: website | X8: WebPage + WebApplication + FAQPage + BreadcrumbList | Y8: Inicio › Calculadoras › Fecha de pago de la planilla | Z8: Anual (cargar festivos del año siguiente antes del 1-dic) | AA8: Alimenta el recordatorio de pago (registro). URL sin año.
A9: P06 | B9: Glosario: SLN | C9: https://frilo.dev/glosario/sln | D9: /glosario/sln | E9: Glosario | F9: GlosarioSLN.dc.html | G9: Wireframe aprobado (falta tabla de siglas) | H9: index, follow | I9: Sí | J9: https://frilo.dev/glosario/sln | K9: 3 - Media-baja | L9: sln en planilla de seguridad social | M9: Casi exacta: "SLN en la planilla de seguridad social" | N9: =IFERROR(INDEX(Keywords!$F$2:$F$107,MATCH(L9,Keywords!$A$2:$A$107,0)),"s/d") -> 210 | O9: =IFERROR(IF(INDEX(Keywords!$G$2:$G$107,MATCH(L9,Keywords!$A$2:$A$107,0))="","s/d",INDEX(Keywords!$G$2:$G$107,MATCH(L9,Keywords!$A$2:$A$107,0))),"s/d") -> 0 | P9: =SUMIFS(Keywords!$F$2:$F$107,Keywords!$C$2:$C$107,A9,Keywords!$D$2:$D$107,"Principal")+SUMIFS(Keywords!$F$2:$F$107,Keywords!$C$2:$C$107,A9,Keywords!$D$2:$D$107,"Secundaria")+SUMIFS(Keywords!$F$2:$F$107,Keywords!$C$2:$C$107,A9,Keywords!$D$2:$D$107,"Soporte (H2/FAQ)") -> 210 | Q9: — | R9: Qué significa SLN en la planilla de seguridad social | Frilo | S9: =LEN(R9) -> 60 | T9: Te explicamos qué significa la novedad SLN en la planilla de seguridad social, cuándo se reporta y cómo afecta tus aportes. | U9: =IF(LEFT(T9,1)="(","",LEN(T9)) -> 123 | V9: Qué significa SLN en la planilla de seguridad social | W9: article | X9: WebPage + DefinedTerm (en DefinedTermSet) + BreadcrumbList | Y9: Inicio › Glosario › SLN | Z9: Cuando cambie la resolución de la PILA | AA9: Pendiente: lista completa de siglas de novedades PILA.
A10: P07 | B10: Dólar hoy | C10: https://frilo.dev/dolar-hoy | D10: /dolar-hoy | E10: Utilidad con datos en vivo | F10: DolarHoy.dc.html | G10: Wireframe aprobado | H10: index, follow | I10: Sí | J10: https://frilo.dev/dolar-hoy | K10: 2 - Media | L10: dolar hoy colombia | M10: Exacta: "Dólar hoy en Colombia" | N10: =IFERROR(INDEX(Keywords!$F$2:$F$107,MATCH(L10,Keywords!$A$2:$A$107,0)),"s/d") -> 1000000 | O10: =IFERROR(IF(INDEX(Keywords!$G$2:$G$107,MATCH(L10,Keywords!$A$2:$A$107,0))="","s/d",INDEX(Keywords!$G$2:$G$107,MATCH(L10,Keywords!$A$2:$A$107,0))),"s/d") -> 46 | P10: =SUMIFS(Keywords!$F$2:$F$107,Keywords!$C$2:$C$107,A10,Keywords!$D$2:$D$107,"Principal")+SUMIFS(Keywords!$F$2:$F$107,Keywords!$C$2:$C$107,A10,Keywords!$D$2:$D$107,"Secundaria")+SUMIFS(Keywords!$F$2:$F$107,Keywords!$C$2:$C$107,A10,Keywords!$D$2:$D$107,"Soporte (H2/FAQ)") -> 3093600 | Q10: precio dolar hoy colombia; precio del dolar colombiano hoy; valor del dolar hoy; valor del dolar hoy colombia | R10: Dólar hoy en Colombia: precio y TRM actualizada | Frilo | S10: =LEN(R10) -> 55 | T10: Consulta el precio del dólar hoy en Colombia y la TRM oficial del día, con histórico, conversor de dólares a pesos y alertas por correo. | U10: =IF(LEFT(T10,1)="(","",LEN(T10)) -> 136 | V10: Dólar hoy en Colombia: TRM del [fecha dinámica] | W10: website | X10: WebPage + FAQPage + BreadcrumbList + Dataset (opcional) | Y10: Inicio › Dólar hoy | Z10: Diaria (revalidate 86400 s) | AA10: KD 46 a 74 y conversor de Google en la SERP: tomar la estimación de clics como techo. Página única, sin URLs por fecha.
A11: P08 | B11: Cuenta en dólares | C11: https://frilo.dev/guias/cuenta-en-dolares-colombia | D11: /guias/cuenta-en-dolares-colombia | E11: Guía comparativa | F11: GuiaCuentaDolares.dc.html | G11: Wireframe aprobado | H11: index, follow | I11: Sí | J11: https://frilo.dev/guias/cuenta-en-dolares-colombia | K11: 3 - Media-baja | L11: cuenta en dolares en colombia | M11: Exacta: "Cuenta en dólares en Colombia" | N11: =IFERROR(INDEX(Keywords!$F$2:$F$107,MATCH(L11,Keywords!$A$2:$A$107,0)),"s/d") -> 320 | O11: =IFERROR(IF(INDEX(Keywords!$G$2:$G$107,MATCH(L11,Keywords!$A$2:$A$107,0))="","s/d",INDEX(Keywords!$G$2:$G$107,MATCH(L11,Keywords!$A$2:$A$107,0))),"s/d") -> 0 | P11: =SUMIFS(Keywords!$F$2:$F$107,Keywords!$C$2:$C$107,A11,Keywords!$D$2:$D$107,"Principal")+SUMIFS(Keywords!$F$2:$F$107,Keywords!$C$2:$C$107,A11,Keywords!$D$2:$D$107,"Secundaria")+SUMIFS(Keywords!$F$2:$F$107,Keywords!$C$2:$C$107,A11,Keywords!$D$2:$D$107,"Soporte (H2/FAQ)") -> 1050 | Q11: cuenta en dolares (390); cuenta de ahorros en dolares (90); como abrir una cuenta en dolares en colombia (70) | R11: Cuenta en dólares en Colombia: opciones y requisitos | Frilo | S11: =LEN(R11) -> 60 | T11: Compara las opciones para tener una cuenta en dólares en Colombia: requisitos, costos y tiempos de apertura. Guía para freelancers en 2026. | U11: =IF(LEFT(T11,1)="(","",LEN(T11)) -> 139 | V11: Cuenta en dólares en Colombia: opciones, requisitos y costos | W11: article | X11: Article + FAQPage + BreadcrumbList | Y11: Inicio › Guías › Cuenta en dólares | Z11: Trimestral (requisitos y costos de cada entidad) | AA11: La keyword de más volumen es de marca ("cuenta en dolares bancolombia", 720): solo en la tabla, nunca en title, H1 ni URL.
A12: P09 | B12: Recibir pagos en dólares | C12: https://frilo.dev/guias/recibir-pagos-en-dolares-colombia | D12: /guias/recibir-pagos-en-dolares-colombia | E12: Guía | F12: GuiaRecibirDolares.dc.html | G12: Wireframe aprobado | H12: index, follow | I12: Sí | J12: https://frilo.dev/guias/recibir-pagos-en-dolares-colombia | K12: 2 - Media | L12: como recibir pagos en dolares en colombia | M12: Parcial: el H1 dice "Cómo recibir pagos del exterior en dólares en Colombia" | N12: =IFERROR(INDEX(Keywords!$F$2:$F$107,MATCH(L12,Keywords!$A$2:$A$107,0)),"s/d") -> 10 | O12: =IFERROR(IF(INDEX(Keywords!$G$2:$G$107,MATCH(L12,Keywords!$A$2:$A$107,0))="","s/d",INDEX(Keywords!$G$2:$G$107,MATCH(L12,Keywords!$A$2:$A$107,0))),"s/d") -> s/d | P12: =SUMIFS(Keywords!$F$2:$F$107,Keywords!$C$2:$C$107,A12,Keywords!$D$2:$D$107,"Principal")+SUMIFS(Keywords!$F$2:$F$107,Keywords!$C$2:$C$107,A12,Keywords!$D$2:$D$107,"Secundaria")+SUMIFS(Keywords!$F$2:$F$107,Keywords!$C$2:$C$107,A12,Keywords!$D$2:$D$107,"Soporte (H2/FAQ)") -> 10 | Q12: — | R12: Cómo recibir pagos del exterior en dólares en Colombia | Frilo | S12: =LEN(R12) -> 62 | T12: Recibe pagos del exterior en dólares en Colombia: opciones, costos, tiempos y qué debes declarar. Guía para freelancers e independientes. | U12: =IF(LEFT(T12,1)="(","",LEN(T12)) -> 137 | V12: Cómo recibir pagos del exterior en dólares en Colombia | W12: article | X12: Article + FAQPage + BreadcrumbList | Y12: Inicio › Guías › Recibir pagos en dólares | Z12: Trimestral | AA12: Volumen bajo (10) pero es el tema con más encaje con el perfil que cobra en dólares. Medir en Ranki "recibir pagos del exterior colombia" y "recibir dólares en colombia".
A13: P10 | B13: Calculadora de interés compuesto | C13: https://frilo.dev/calculadoras/interes-compuesto | D13: /calculadoras/interes-compuesto | E13: Herramienta | F13: InteresCompuesto.dc.html | G13: Wireframe aprobado | H13: index, follow | I13: Sí | J13: https://frilo.dev/calculadoras/interes-compuesto | K13: 1 - Alta | L13: calculadora interés compuesto | M13: Casi exacta: "Calculadora de interés compuesto" | N13: =IFERROR(INDEX(Keywords!$F$2:$F$107,MATCH(L13,Keywords!$A$2:$A$107,0)),"s/d") -> 5400 | O13: =IFERROR(IF(INDEX(Keywords!$G$2:$G$107,MATCH(L13,Keywords!$A$2:$A$107,0))="","s/d",INDEX(Keywords!$G$2:$G$107,MATCH(L13,Keywords!$A$2:$A$107,0))),"s/d") -> s/d | P13: =SUMIFS(Keywords!$F$2:$F$107,Keywords!$C$2:$C$107,A13,Keywords!$D$2:$D$107,"Principal")+SUMIFS(Keywords!$F$2:$F$107,Keywords!$C$2:$C$107,A13,Keywords!$D$2:$D$107,"Secundaria")+SUMIFS(Keywords!$F$2:$F$107,Keywords!$C$2:$C$107,A13,Keywords!$D$2:$D$107,"Soporte (H2/FAQ)") -> 5500 | Q13: simulador de ahorro (50, title); calculadora de ahorro (50) | R13: Calculadora de interés compuesto y simulador de ahorro | Frilo | S13: =LEN(R13) -> 62 | T13: Simula cuánto crece tu ahorro con interés compuesto: monto inicial, aporte mensual, tasa efectiva anual y plazo. Gratis y sin registro. | U13: =IF(LEFT(T13,1)="(","",LEN(T13)) -> 135 | V13: Calculadora de interés compuesto: simula cuánto rinde tu ahorro | W13: website | X13: WebPage + WebApplication + FAQPage + BreadcrumbList | Y13: Inicio › Calculadoras › Interés compuesto | Z13: Cuando cambien las tasas de referencia o la retención | AA13: Mayor volumen del sitio sin contar dólar hoy (5.400). La SERP no tiene un competidor colombiano con contexto local.
... A24: APP | B24: App web (herramienta) | C24: https://app.frilo.dev | D24: app.frilo.dev | E24: App web | F24: Repositorio actual de la app | G24: Existe en frilo.dev; mover | H24: noindex, nofollow (meta + cabecera X-Robots-Tag) | I24: No | J24: — (no aplica) | K24: Recomendación | L24: No aplica | M24: — | N24: =IFERROR(INDEX(Keywords!$F$2:$F$107,MATCH(L24,Keywords!$A$2:$A$107,0)),"s/d") -> s/d | O24: =IFERROR(IF(INDEX(Keywords!$G$2:$G$107,MATCH(L24,Keywords!$A$2:$A$107,0))="","s/d",INDEX(Keywords!$G$2:$G$107,MATCH(L24,Keywords!$A$2:$A$107,0))),"s/d") -> s/d | P24: =SUMIFS(Keywords!$F$2:$F$107,Keywords!$C$2:$C$107,A24,Keywords!$D$2:$D$107,"Principal")+SUMIFS(Keywords!$F$2:$F$107,Keywords!$C$2:$C$107,A24,Keywords!$D$2:$D$107,"Secundaria")+SUMIFS(Keywords!$F$2:$F$107,Keywords!$C$2:$C$107,A24,Keywords!$D$2:$D$107,"Soporte (H2/FAQ)") -> 0 | Q24: — | R24: (definido por la app) | S24: =LEN(R24) -> 21 | T24: (no aplica) | U24: =IF(LEFT(T24,1)="(","",LEN(T24)) | V24: (no aplica) | W24: — | X24: Ninguno | Y24: — | Z24: — | AA24: Ver hoja "App y ambientes". Todos los CTA "Probar la app gratis" y "Entrar" apuntan aquí.
A26: Rangos: title de 55 a 65 caracteres con " | Frilo"; meta description de 120 a 150. Verde = en rango; rojo = fuera de rango en una página indexable (las legales se aceptan cortas). El año va en title y H1, nunca en la URL.

Sheet Datos estructurados
A1: ID | B1: URL final | C1: Tipos | D1: JSON-LD para <script type="application/ld+json"> | E1: Notas
A2: Home | B2: =URLs!C2 -> https://frilo.dev/ | C2: Organization + WebSite + Person + WebPage + FAQPage | D2: { "@context": "https://schema.org", "@graph": [ { "@type": "Organization", "@id": "https://frilo.dev/#organization", "name": "Frilo", "url": "https://frilo.dev", "logo": "https://frilo.dev/logos/isotipo-oliva.png", "slogan": "Tus finanzas, mejor con Frilo", "areaServed": "CO" }, { "@type": "WebSite", "@id": "https://frilo.dev/#website", "url": "https://frilo.dev", "name": "Frilo", "inLanguage": "es-CO", "publisher": { "@id": "https://frilo.dev/#organization" } }, { "@type": "Person", "@id": "https://frilo.dev/#nicolas", "name": "Nicolás Suárez", "jobTitle": "Fundador de Frilo", "url": "https://frilo.dev/quienes-somos" }, { "@type": "WebPage", "@id": "https://frilo.dev", "url": "https://frilo.dev", "name": "Frilo", "description": "Calcula tu planilla de independiente, aparta tu prima y tus cesantías y sigue el dólar. Gratis, en pesos o en dólares, sin registro.", "inLanguage": "es-CO", "isPartOf": { "@id": "https://frilo.dev/#website" }, "dateModified": "2026-10-20" }, { "@type": "FAQPage", "@id": "https://frilo.dev/#faq", "mainEntity": [ { "@type": "Question", "name": "¿Frilo es gratis?", "acceptedAnswer": { "@type": "Answer", "text": "Sí. Las calculadoras se usan sin registro. Crear una cuenta es gratis y sirve para guardar tus cálculos y recibir alertas." } }, { "@type": "Question", "name": "¿Las cuentas que recomienda Frilo le pagan?", "acceptedAnswer": { "@type": "Answer", "text": "No. Frilo es un proyecto nuevo y gratuito: ninguna entidad nos paga por aparecer y el orden de las comparativas es siempre por tasa. No vendemos tus datos." } }, { "@type": "Question", "name": "¿Frilo paga mi planilla?", "acceptedAnswer": { "@type": "Answer", "text": "No. Calcula el valor y te lleva al operador para que la pagues tú." } }, { "@type": "Question", "name": "¿Sirve si me pagan en pesos?", "acceptedAnswer": { "@type": "Answer", "text": "Sí. Funciona para contratos de prestación de servicios en pesos, en dólares o de ambas formas." } }, { "@type": "Question", "name": "¿De dónde sale la TRM?", "acceptedAnswer": { "@type": "Answer", "text": "Del dato oficial que publica la Superintendencia Financiera en Datos Abiertos Colombia." } }, { "@type": "Question", "name": "¿Es asesoría financiera?", "acceptedAnswer": { "@type": "Answer", "text": "No. Son cálculos y simulaciones con fines informativos." } } ] } ] } | E2: Un solo script por página. Organization, WebSite y Person van en todas las páginas con el mismo @id. dateModified y lastReviewed = fecha real de la última edición (la misma visible en la página). FAQPage con las preguntas visibles del wireframe: si el texto cambia en el código, regenerar.
A3: Hub-C | B3: =URLs!C3 -> https://frilo.dev/calculadoras | C3: CollectionPage + ItemList + BreadcrumbList | D3: { "@context": "https://schema.org", "@graph": [ { "@type": "Organization", "@id": "https://frilo.dev/#organization", "name": "Frilo", "url": "https://frilo.dev", "logo": "https://frilo.dev/logos/isotipo-oliva.png", "slogan": "Tus finanzas, mejor con Frilo", "areaServed": "CO" }, { "@type": "WebSite", "@id": "https://frilo.dev/#website", "url": "https://frilo.dev", "name": "Frilo", "inLanguage": "es-CO", "publisher": { "@id": "https://frilo.dev/#organization" } }, { "@type": "Person", "@id": "https://frilo.dev/#nicolas", "name": "Nicolás Suárez", "jobTitle": "Fundador de Frilo", "url": "https://frilo.dev/quienes-somos" }, { "@type": "CollectionPage", "@id": "https://frilo.dev/calculadoras", "url": "https://frilo.dev/calculadoras", "name": "Calculadoras para independientes y contratistas en Colombia", "description": "Calculadoras gratis para independientes en Colombia: aportes, fecha de pago de la planilla, cesantías e intereses y dólar hoy. Sin registro.", "inLanguage": "es-CO", "isPartOf": { "@id": "https://frilo.dev/#website" }, "dateModified": "2026-10-20", "mainEntity": { "@type": "ItemList", "itemListElement": [ { "@type": "ListItem", "position": 1, "url": "https://frilo.dev/calculadoras/aportes-independientes", "name": "Calculadora de aportes para independientes 2026" }, { "@type": "ListItem", "position": 2, "url": "https://frilo.dev/calculadoras/fecha-pago-planilla", "name": "Fechas de pago de la planilla de seguridad social 2026" }, { "@type": "ListItem", "position": 3, "url": "https://frilo.dev/calculadoras/cesantias", "name": "Calculadora de cesantías e intereses de cesantías 2026" }, { "@type": "ListItem", "position": 4, "url": "https://frilo.dev/calculadoras/interes-compuesto", "name": "Calculadora de interés compuesto: simula cuánto rinde tu ahorro" }, { "@type": "ListItem", "position": 5, "url": "https://frilo.dev/dolar-hoy", "name": "Dólar hoy en Colombia: TRM del [fecha dinámica]" } ] } }, { "@type": "BreadcrumbList", "itemListElement": [ { "@type": "ListItem", "position": 1, "name": "Inicio", "item": "https://frilo.dev" }, { "@type": "ListItem", "position": 2, "name": "Calculadoras" } ] } ] } | E3: Un solo script por página. Organization, WebSite y Person van en todas las páginas con el mismo @id. dateModified y lastReviewed = fecha real de la última edición (la misma visible en la página). FAQPage con las preguntas visibles del wireframe: si el texto cambia en el código, regenerar.
A4: P01 | B4: =URLs!C4 -> https://frilo.dev/calculadoras/aportes-independientes | C4: WebPage + WebApplication + FAQPage + BreadcrumbList | D4: { "@context": "https://schema.org", "@graph": [ { "@type": "Organization", "@id": "https://frilo.dev/#organization", "name": "Frilo", "url": "https://frilo.dev", "logo": "https://frilo.dev/logos/isotipo-oliva.png", "slogan": "Tus finanzas, mejor con Frilo", "areaServed": "CO" }, { "@type": "WebSite", "@id": "https://frilo.dev/#website", "url": "https://frilo.dev", "name": "Frilo", "inLanguage": "es-CO", "publisher": { "@id": "https://frilo.dev/#organization" } }, { "@type": "Person", "@id": "https://frilo.dev/#nicolas", "name": "Nicolás Suárez", "jobTitle": "Fundador de Frilo", "url": "https://frilo.dev/quienes-somos" }, { "@type": "WebPage", "@id": "https://frilo.dev/calculadoras/aportes-independientes", "url": "https://frilo.dev/calculadoras/aportes-independientes", "name": "Calculadora de aportes para independientes 2026", "description": "Calcula cuánto pagas de salud, pensión, ARL y Fondo de Solidaridad como independiente o contratista en 2026. Gratis y sin registro.", "inLanguage": "es-CO", "isPartOf": { "@id": "https://frilo.dev/#website" }, "dateModified": "2026-10-20", "mainEntity": { "@id": "https://frilo.dev/calculadoras/aportes-independientes#app" }, "author": { "@id": "https://frilo.dev/#nicolas" }, "reviewedBy": { "@type": "Organization", "name": "Equipo de finanzas Frilo", "parentOrganization": { "@id": "https://frilo.dev/#organization" } }, "lastReviewed": "2026-10-20" }, { "@type": "WebApplication", "@id": "https://frilo.dev/calculadoras/aportes-independientes#app", "name": "Calculadora de aportes para independientes 2026", "url": "https://frilo.dev/calculadoras/aportes-independientes", "applicationCategory": "FinanceApplication", "operatingSystem": "Web", "inLanguage": "es-CO", "isAccessibleForFree": true, "offers": { "@type": "Offer", "price": "0", "priceCurrency": "COP" }, "publisher": { "@id": "https://frilo.dev/#organization" }, "dateModified": "2026-10-20" }, { "@type": "BreadcrumbList", "itemListElement": [ { "@type": "ListItem", "position": 1, "name": "Inicio", "item": "https://frilo.dev" }, { "@type": "ListItem", "position": 2, "name": "Calculadoras", "item": "https://frilo.dev/calculadoras" }, { "@type": "ListItem", "position": 3, "name": "Aportes para independientes" } ] }, { "@type": "FAQPage", "@id": "https://frilo.dev/calculadoras/aportes-independientes#faq", "mainEntity": [ { "@type": "Question", "name": "¿Puedo calcular la liquidación de mi planilla antes de pagar?", "acceptedAnswer": { "@type": "Answer", "text": "Sí. Esta calculadora hace la liquidación de aportes con las tarifas y el redondeo de la PILA. El valor final lo confirma el operador al liquidar tu planilla." } }, { "@type": "Question", "name": "¿El resultado es el mismo que me da Mi Planilla o SOI?", "acceptedAnswer": { "@type": "Answer", "text": "Usamos la misma fórmula (40% del ingreso, tarifas de 2026 y redondeo a 100). Puede haber diferencias si reportas novedades, días incompletos o una clase de riesgo distinta." } }, { "@type": "Question", "name": "¿Tengo que pagar ARL si trabajo desde mi casa?", "acceptedAnswer": { "@type": "Answer", "text": "Depende de tu contrato. Si tienes un contrato de prestación de servicios de más de un mes, la ARL es obligatoria (Decreto 723 de 2013): en riesgo I a III la pagas tú y en IV y V la paga el contratante. Si trabajas por tu cuenta, sin contrato, en riesgo I a III es voluntaria." } }, { "@type": "Question", "name": "¿Qué pasa si facturo menos de un salario mínimo?", "acceptedAnswer": { "@type": "Answer", "text": "Cotizas igual sobre un salario mínimo ($1.750.905 en 2026), porque es la base mínima de cotización. Por eso la calculadora nunca usa un IBC menor." } }, { "@type": "Question", "name": "¿Cómo cotizo si tengo varios contratos?", "acceptedAnswer": { "@type": "Answer", "text": "Sumas lo que facturas en el mes por todos tus contratos y sacas el 40% de esa suma. El IBC sigue con el tope de 25 salarios mínimos." } }, { "@type": "Question", "name": "¿Si me pagan en dólares, qué TRM uso?", "acceptedAnswer": { "@type": "Answer", "text": "Usa el valor en pesos de lo que recibiste. Si necesitas convertir, toma la TRM del día en que te pagaron. Puedes consultarla en dólar hoy en Colombia." } }, { "@type": "Question", "name": "¿Y si trabajo por cuenta propia, sin contrato de prestación de servicios?", "acceptedAnswer": { "@type": "Answer", "text": "Desde el Decreto 379 de 2026, primero descuentas tus costos (o aplicas la presunción de costos de la UGPP) y sacas el 40% del ingreso neto. Esta calculadora está pensada para contratistas de prestación de servicios." } } ] } ] } | E4: Un solo script por página. Organization, WebSite y Person van en todas las páginas con el mismo @id. dateModified y lastReviewed = fecha real de la última edición (la misma visible en la página). FAQPage con las preguntas visibles del wireframe: si el texto cambia en el código, regenerar.
A5: P02 | B5: =URLs!C5 -> https://frilo.dev/guias/ibc-independientes | C5: Article + FAQPage + BreadcrumbList | D5: { "@context": "https://schema.org", "@graph": [ { "@type": "Organization", "@id": "https://frilo.dev/#organization", "name": "Frilo", "url": "https://frilo.dev", "logo": "https://frilo.dev/logos/isotipo-oliva.png", "slogan": "Tus finanzas, mejor con Frilo", "areaServed": "CO" }, { "@type": "WebSite", "@id": "https://frilo.dev/#website", "url": "https://frilo.dev", "name": "Frilo", "inLanguage": "es-CO", "publisher": { "@id": "https://frilo.dev/#organization" } }, { "@type": "Person", "@id": "https://frilo.dev/#nicolas", "name": "Nicolás Suárez", "jobTitle": "Fundador de Frilo", "url": "https://frilo.dev/quienes-somos" }, { "@type": "WebPage", "@id": "https://frilo.dev/guias/ibc-independientes", "url": "https://frilo.dev/guias/ibc-independientes", "name": "IBC para independientes 2026: qué es y cómo calcularlo", "description": "Qué es el IBC de un independiente, cómo calcularlo en 2026 con el 40% de tus ingresos y cómo cambiarlo en SOI. Con calculadora gratis.", "inLanguage": "es-CO", "isPartOf": { "@id": "https://frilo.dev/#website" }, "dateModified": "2026-10-20", "reviewedBy": { "@type": "Organization", "name": "Equipo de finanzas Frilo", "parentOrganization": { "@id": "https://frilo.dev/#organization" } }, "lastReviewed": "2026-10-20", "mainEntity": { "@id": "https://frilo.dev/guias/ibc-independientes#article" } }, { "@type": "Article", "@id": "https://frilo.dev/guias/ibc-independientes#article", "headline": "IBC para independientes 2026: qué es y cómo calcularlo", "description": "Qué es el IBC de un independiente, cómo calcularlo en 2026 con el 40% de tus ingresos y cómo cambiarlo en SOI. Con calculadora gratis.", "mainEntityOfPage": "https://frilo.dev/guias/ibc-independientes", "inLanguage": "es-CO", "author": { "@id": "https://frilo.dev/#nicolas" }, "publisher": { "@id": "https://frilo.dev/#organization" }, "datePublished": "2026-10-20", "dateModified": "2026-10-20", "image": "https://frilo.dev/og/guias/ibc-independientes.png" }, { "@type": "BreadcrumbList", "itemListElement": [ { "@type": "ListItem", "position": 1, "name": "Inicio", "item": "https://frilo.dev" }, { "@type": "ListItem", "position": 2, "name": "Guías", "item": "https://frilo.dev/guias" }, { "@type": "ListItem", "position": 3, "name": "IBC para independientes" } ] }, { "@type": "FAQPage", "@id": "https://frilo.dev/guias/ibc-independientes#faq", "mainEntity": [ { "@type": "Question", "name": "¿El IBC se calcula sobre lo facturado o sobre lo recibido?", "acceptedAnswer": { "@type": "Answer", "text": "Si tienes contrato de prestación de servicios, sobre el 40% del valor mensualizado del contrato, sin IVA. Como cotizas mes vencido, pagas en la planilla del mes siguiente. Si trabajas por cuenta propia, sin contrato de prestación de servicios, primero descuentas tus costos y sacas el 40% del ingreso neto (Decreto 379 de 2026)." } }, { "@type": "Question", "name": "¿Puedo cotizar sobre un IBC mayor al 40%?", "acceptedAnswer": { "@type": "Answer", "text": "Sí. El 40% es la base mínima, no la máxima (artículo 89 de la Ley 2277 de 2022). Puedes cotizar sobre más para mejorar tu pensión futura, sin pasar de 25 salarios mínimos ($43.772.625 en 2026)." } }, { "@type": "Question", "name": "¿Qué pasa si no reporto bien mi IBC?", "acceptedAnswer": { "@type": "Answer", "text": "La UGPP fiscaliza los aportes de los independientes y puede cobrar lo que faltó, con intereses y sanciones. Guarda tus facturas y las planillas pagadas." } } ] } ] } | E5: Un solo script por página. Organization, WebSite y Person van en todas las páginas con el mismo @id. dateModified y lastReviewed = fecha real de la última edición (la misma visible en la página). FAQPage con las preguntas visibles del wireframe: si el texto cambia en el código, regenerar.
A6: P03 | B6: =URLs!C6 -> https://frilo.dev/calculadoras/cesantias | C6: WebPage + WebApplication + FAQPage + BreadcrumbList | D6: { "@context": "https://schema.org", "@graph": [ { "@type": "Organization", "@id": "https://frilo.dev/#organization", "name": "Frilo", "url": "https://frilo.dev", "logo": "https://frilo.dev/logos/isotipo-oliva.png", "slogan": "Tus finanzas, mejor con Frilo", "areaServed": "CO" }, { "@type": "WebSite", "@id": "https://frilo.dev/#website", "url": "https://frilo.dev", "name": "Frilo", "inLanguage": "es-CO", "publisher": { "@id": "https://frilo.dev/#organization" } }, { "@type": "Person", "@id": "https://frilo.dev/#nicolas", "name": "Nicolás Suárez", "jobTitle": "Fundador de Frilo", "url": "https://frilo.dev/quienes-somos" }, { "@type": "WebPage", "@id": "https://frilo.dev/calculadoras/cesantias", "url": "https://frilo.dev/calculadoras/cesantias", "name": "Calculadora de cesantías e intereses de cesantías 2026", "description": "Calcula tus cesantías y los intereses del 12% en 2026, con contrato laboral o como independiente. Incluye años anteriores. Sin registro.", "inLanguage": "es-CO", "isPartOf": { "@id": "https://frilo.dev/#website" }, "dateModified": "2026-10-20", "mainEntity": { "@id": "https://frilo.dev/calculadoras/cesantias#app" }, "author": { "@id": "https://frilo.dev/#nicolas" }, "reviewedBy": { "@type": "Organization", "name": "Equipo de finanzas Frilo", "parentOrganization": { "@id": "https://frilo.dev/#organization" } }, "lastReviewed": "2026-10-20" }, { "@type": "WebApplication", "@id": "https://frilo.dev/calculadoras/cesantias#app", "name": "Calculadora de cesantías e intereses de cesantías 2026", "url": "https://frilo.dev/calculadoras/cesantias", "applicationCategory": "FinanceApplication", "operatingSystem": "Web", "inLanguage": "es-CO", "isAccessibleForFree": true, "offers": { "@type": "Offer", "price": "0", "priceCurrency": "COP" }, "publisher": { "@id": "https://frilo.dev/#organization" }, "dateModified": "2026-10-20" }, { "@type": "BreadcrumbList", "itemListElement": [ { "@type": "ListItem", "position": 1, "name": "Inicio", "item": "https://frilo.dev" }, { "@type": "ListItem", "position": 2, "name": "Calculadoras", "item": "https://frilo.dev/calculadoras" }, { "@type": "ListItem", "position": 3, "name": "Cesantías e intereses" } ] }, { "@type": "FAQPage", "@id": "https://frilo.dev/calculadoras/cesantias#faq", "mainEntity": [ { "@type": "Question", "name": "¿Cuándo pagan los intereses de cesantías en 2026?", "acceptedAnswer": { "@type": "Answer", "text": "Los intereses de las cesantías de 2025 se pagan directamente al trabajador a más tardar el 31 de enero de 2026. Las cesantías se consignan al fondo a más tardar el 14 de febrero." } }, { "@type": "Question", "name": "¿Qué pasa si el empleador no consigna las cesantías a tiempo?", "acceptedAnswer": { "@type": "Answer", "text": "Debe pagar una sanción moratoria: un día de salario por cada día de retraso en la consignación (Ley 50 de 1990, artículo 99)." } }, { "@type": "Question", "name": "¿El auxilio de transporte se incluye en las cesantías?", "acceptedAnswer": { "@type": "Answer", "text": "Sí. Si ganas hasta 2 salarios mínimos y tienes derecho al auxilio de transporte ($249.095 en 2026), se suma al salario para liquidar las cesantías y sus intereses." } }, { "@type": "Question", "name": "¿Un independiente tiene derecho a cesantías?", "acceptedAnswer": { "@type": "Answer", "text": "No por su contrato. Puede crear las suyas apartando el 8,33% de cada pago. Ver la guía." } } ] } ] } | E6: Un solo script por página. Organization, WebSite y Person van en todas las páginas con el mismo @id. dateModified y lastReviewed = fecha real de la última edición (la misma visible en la página). FAQPage con las preguntas visibles del wireframe: si el texto cambia en el código, regenerar.
A7: P04 | B7: =URLs!C7 -> https://frilo.dev/guias/descargar-planilla-seguridad-social | C7: Article + FAQPage + BreadcrumbList | D7: { "@context": "https://schema.org", "@graph": [ { "@type": "Organization", "@id": "https://frilo.dev/#organization", "name": "Frilo", "url": "https://frilo.dev", "logo": "https://frilo.dev/logos/isotipo-oliva.png", "slogan": "Tus finanzas, mejor con Frilo", "areaServed": "CO" }, { "@type": "WebSite", "@id": "https://frilo.dev/#website", "url": "https://frilo.dev", "name": "Frilo", "inLanguage": "es-CO", "publisher": { "@id": "https://frilo.dev/#organization" } }, { "@type": "Person", "@id": "https://frilo.dev/#nicolas", "name": "Nicolás Suárez", "jobTitle": "Fundador de Frilo", "url": "https://frilo.dev/quienes-somos" }, { "@type": "WebPage", "@id": "https://frilo.dev/guias/descargar-planilla-seguridad-social", "url": "https://frilo.dev/guias/descargar-planilla-seguridad-social", "name": "Cómo descargar y verificar tu planilla de seguridad social", "description": "Descarga tu planilla de seguridad social, verifica que el pago quedó registrado y conoce qué cambia si eres independiente. Guía 2026.", "inLanguage": "es-CO", "isPartOf": { "@id": "https://frilo.dev/#website" }, "dateModified": "2026-10-20", "reviewedBy": { "@type": "Organization", "name": "Equipo de finanzas Frilo", "parentOrganization": { "@id": "https://frilo.dev/#organization" } }, "lastReviewed": "2026-10-20", "mainEntity": { "@id": "https://frilo.dev/guias/descargar-planilla-seguridad-social#article" } }, { "@type": "Article", "@id": "https://frilo.dev/guias/descargar-planilla-seguridad-social#article", "headline": "Cómo descargar y verificar tu planilla de seguridad social", "description": "Descarga tu planilla de seguridad social, verifica que el pago quedó registrado y conoce qué cambia si eres independiente. Guía 2026.", "mainEntityOfPage": "https://frilo.dev/guias/descargar-planilla-seguridad-social", "inLanguage": "es-CO", "author": { "@id": "https://frilo.dev/#nicolas" }, "publisher": { "@id": "https://frilo.dev/#organization" }, "datePublished": "2026-10-20", "dateModified": "2026-10-20", "image": "https://frilo.dev/og/guias/descargar-planilla-seguridad-social.png" }, { "@type": "BreadcrumbList", "itemListElement": [ { "@type": "ListItem", "position": 1, "name": "Inicio", "item": "https://frilo.dev" }, { "@type": "ListItem", "position": 2, "name": "Guías", "item": "https://frilo.dev/guias" }, { "@type": "ListItem", "position": 3, "name": "Descargar la planilla" } ] }, { "@type": "FAQPage", "@id": "https://frilo.dev/guias/descargar-planilla-seguridad-social#faq", "mainEntity": [ { "@type": "Question", "name": "¿Puedo descargar la planilla si pagué en otro operador?", "acceptedAnswer": { "@type": "Answer", "text": "No. Cada operador guarda solo las planillas que se pagaron con él. Entra al portal del operador donde hiciste el pago." } }, { "@type": "Question", "name": "¿Cuánto tarda en aparecer el pago?", "acceptedAnswer": { "@type": "Answer", "text": "Depende del operador y del medio de pago. Si no aparece, revisa con el número de planilla en el portal del operador o comunícate con su línea de atención." } }, { "@type": "Question", "name": "¿La planilla sirve como certificado para mi contratante?", "acceptedAnswer": { "@type": "Answer", "text": "Sí. Los contratantes suelen pedir la planilla pagada del periodo para pagar tus honorarios, porque deben verificar que cotizaste." } } ] } ] } | E7: Un solo script por página. Organization, WebSite y Person van en todas las páginas con el mismo @id. dateModified y lastReviewed = fecha real de la última edición (la misma visible en la página). FAQPage con las preguntas visibles del wireframe: si el texto cambia en el código, regenerar.
A8: P05 | B8: =URLs!C8 -> https://frilo.dev/calculadoras/fecha-pago-planilla | C8: WebPage + WebApplication + FAQPage + BreadcrumbList | D8: { "@context": "https://schema.org", "@graph": [ { "@type": "Organization", "@id": "https://frilo.dev/#organization", "name": "Frilo", "url": "https://frilo.dev", "logo": "https://frilo.dev/logos/isotipo-oliva.png", "slogan": "Tus finanzas, mejor con Frilo", "areaServed": "CO" }, { "@type": "WebSite", "@id": "https://frilo.dev/#website", "url": "https://frilo.dev", "name": "Frilo", "inLanguage": "es-CO", "publisher": { "@id": "https://frilo.dev/#organization" } }, { "@type": "Person", "@id": "https://frilo.dev/#nicolas", "name": "Nicolás Suárez", "jobTitle": "Fundador de Frilo", "url": "https://frilo.dev/quienes-somos" }, { "@type": "WebPage", "@id": "https://frilo.dev/calculadoras/fecha-pago-planilla", "url": "https://frilo.dev/calculadoras/fecha-pago-planilla", "name": "Fechas de pago de la planilla de seguridad social 2026", "description": "Consulta la fecha límite para pagar la planilla de seguridad social en 2026 según los últimos dígitos de tu documento. Calendario completo.", "inLanguage": "es-CO", "isPartOf": { "@id": "https://frilo.dev/#website" }, "dateModified": "2026-10-20", "mainEntity": { "@id": "https://frilo.dev/calculadoras/fecha-pago-planilla#app" }, "author": { "@id": "https://frilo.dev/#nicolas" }, "reviewedBy": { "@type": "Organization", "name": "Equipo de finanzas Frilo", "parentOrganization": { "@id": "https://frilo.dev/#organization" } }, "lastReviewed": "2026-10-20" }, { "@type": "WebApplication", "@id": "https://frilo.dev/calculadoras/fecha-pago-planilla#app", "name": "Fechas de pago de la planilla de seguridad social 2026", "url": "https://frilo.dev/calculadoras/fecha-pago-planilla", "applicationCategory": "FinanceApplication", "operatingSystem": "Web", "inLanguage": "es-CO", "isAccessibleForFree": true, "offers": { "@type": "Offer", "price": "0", "priceCurrency": "COP" }, "publisher": { "@id": "https://frilo.dev/#organization" }, "dateModified": "2026-10-20" }, { "@type": "BreadcrumbList", "itemListElement": [ { "@type": "ListItem", "position": 1, "name": "Inicio", "item": "https://frilo.dev" }, { "@type": "ListItem", "position": 2, "name": "Calculadoras", "item": "https://frilo.dev/calculadoras" }, { "@type": "ListItem", "position": 3, "name": "Fecha de pago de la planilla" } ] }, { "@type": "FAQPage", "@id": "https://frilo.dev/calculadoras/fecha-pago-planilla#faq", "mainEntity": [ { "@type": "Question", "name": "¿Qué pasa si la fecha cae en festivo?", "acceptedAnswer": { "@type": "Answer", "text": "No puede caer en festivo: el plazo se cuenta en días hábiles, así que los sábados, domingos y festivos no cuentan. Por eso tu fecha cambia de un mes a otro aunque tus dígitos sean los mismos." } }, { "@type": "Question", "name": "¿Uso los dígitos de la cédula o del NIT?", "acceptedAnswer": { "@type": "Answer", "text": "Los dos últimos dígitos del documento con el que pagas la planilla. Si pagas con tu NIT, toma los dos últimos dígitos incluyendo el dígito de verificación." } }, { "@type": "Question", "name": "¿Puedo pagar antes de mi fecha?", "acceptedAnswer": { "@type": "Answer", "text": "Sí. La fecha es el límite, no el único día posible. Puedes pagar desde que el operador habilita el periodo." } }, { "@type": "Question", "name": "¿Frilo me puede avisar cada mes?", "acceptedAnswer": { "@type": "Answer", "text": "Sí. Crea tu cuenta gratis, escribe los dos últimos dígitos de tu documento y te enviamos un correo 3 días hábiles antes y el mismo día de tu fecha límite." } } ] } ] } | E8: Un solo script por página. Organization, WebSite y Person van en todas las páginas con el mismo @id. dateModified y lastReviewed = fecha real de la última edición (la misma visible en la página). FAQPage con las preguntas visibles del wireframe: si el texto cambia en el código, regenerar.
A9: P06 | B9: =URLs!C9 -> https://frilo.dev/glosario/sln | C9: WebPage + DefinedTerm (en DefinedTermSet) + BreadcrumbList | D9: { "@context": "https://schema.org", "@graph": [ { "@type": "Organization", "@id": "https://frilo.dev/#organization", "name": "Frilo", "url": "https://frilo.dev", "logo": "https://frilo.dev/logos/isotipo-oliva.png", "slogan": "Tus finanzas, mejor con Frilo", "areaServed": "CO" }, { "@type": "WebSite", "@id": "https://frilo.dev/#website", "url": "https://frilo.dev", "name": "Frilo", "inLanguage": "es-CO", "publisher": { "@id": "https://frilo.dev/#organization" } }, { "@type": "Person", "@id": "https://frilo.dev/#nicolas", "name": "Nicolás Suárez", "jobTitle": "Fundador de Frilo", "url": "https://frilo.dev/quienes-somos" }, { "@type": "WebPage", "@id": "https://frilo.dev/glosario/sln", "url": "https://frilo.dev/glosario/sln", "name": "Qué significa SLN en la planilla de seguridad social", "description": "Te explicamos qué significa la novedad SLN en la planilla de seguridad social, cuándo se reporta y cómo afecta tus aportes.", "inLanguage": "es-CO", "isPartOf": { "@id": "https://frilo.dev/#website" }, "dateModified": "2026-10-20", "author": { "@id": "https://frilo.dev/#nicolas" }, "reviewedBy": { "@type": "Organization", "name": "Equipo de finanzas Frilo", "parentOrganization": { "@id": "https://frilo.dev/#organization" } }, "lastReviewed": "2026-10-20", "mainEntity": { "@id": "https://frilo.dev/glosario/sln#term" } }, { "@type": "DefinedTerm", "@id": "https://frilo.dev/glosario/sln#term", "name": "SLN", "alternateName": "Suspensión temporal del contrato o licencia no remunerada", "description": "[Primera oración visible de la página]", "inDefinedTermSet": { "@type": "DefinedTermSet", "@id": "https://frilo.dev/glosario", "name": "Glosario de seguridad social para independientes" } }, { "@type": "BreadcrumbList", "itemListElement": [ { "@type": "ListItem", "position": 1, "name": "Inicio", "item": "https://frilo.dev" }, { "@type": "ListItem", "position": 2, "name": "Glosario", "item": "https://frilo.dev/glosario" }, { "@type": "ListItem", "position": 3, "name": "SLN" } ] } ] } | E9: Un solo script por página. Organization, WebSite y Person van en todas las páginas con el mismo @id. dateModified y lastReviewed = fecha real de la última edición (la misma visible en la página). FAQPage con las preguntas visibles del wireframe: si el texto cambia en el código, regenerar. description = primera oración visible.
A10: P07 | B10: =URLs!C10 -> https://frilo.dev/dolar-hoy | C10: WebPage + FAQPage + BreadcrumbList + Dataset (opcional) | D10: { "@context": "https://schema.org", "@graph": [ { "@type": "Organization", "@id": "https://frilo.dev/#organization", "name": "Frilo", "url": "https://frilo.dev", "logo": "https://frilo.dev/logos/isotipo-oliva.png", "slogan": "Tus finanzas, mejor con Frilo", "areaServed": "CO" }, { "@type": "WebSite", "@id": "https://frilo.dev/#website", "url": "https://frilo.dev", "name": "Frilo", "inLanguage": "es-CO", "publisher": { "@id": "https://frilo.dev/#organization" } }, { "@type": "Person", "@id": "https://frilo.dev/#nicolas", "name": "Nicolás Suárez", "jobTitle": "Fundador de Frilo", "url": "https://frilo.dev/quienes-somos" }, { "@type": "WebPage", "@id": "https://frilo.dev/dolar-hoy", "url": "https://frilo.dev/dolar-hoy", "name": "Dólar hoy en Colombia: TRM del [fecha dinámica]", "description": "Consulta el precio del dólar hoy en Colombia y la TRM oficial del día, con histórico, conversor de dólares a pesos y alertas por correo.", "inLanguage": "es-CO", "isPartOf": { "@id": "https://frilo.dev/#website" }, "dateModified": "2026-10-20", "author": { "@id": "https://frilo.dev/#nicolas" }, "reviewedBy": { "@type": "Organization", "name": "Equipo de finanzas Frilo", "parentOrganization": { "@id": "https://frilo.dev/#organization" } } }, { "@type": "Dataset", "name": "TRM de los últimos 30 días", "description": "Tasa Representativa del Mercado (pesos por dólar) certificada por la Superintendencia Financiera de Colombia.", "creator": { "@type": "GovernmentOrganization", "name": "Superintendencia Financiera de Colombia" }, "distribution": { "@type": "DataDownload", "encodingFormat": "application/json", "contentUrl": "https://www.datos.gov.co/resource/32sa-8pi3.json" }, "temporalCoverage": "[últimos 30 días, dinámico]", "dateModified": "[fecha de la TRM, dinámica]" }, { "@type": "BreadcrumbList", "itemListElement": [ { "@type": "ListItem", "position": 1, "name": "Inicio", "item": "https://frilo.dev" }, { "@type": "ListItem", "position": 2, "name": "Dólar hoy" } ] }, { "@type": "FAQPage", "@id": "https://frilo.dev/dolar-hoy#faq", "mainEntity": [ { "@type": "Question", "name": "¿A cómo está el dólar en Colombia hoy?", "acceptedAnswer": { "@type": "Answer", "text": "Hoy la TRM está en [X.XXX,XX] pesos por dólar, vigente desde el [fecha]." } }, { "@type": "Question", "name": "¿La TRM es el precio al que me compran los dólares?", "acceptedAnswer": { "@type": "Answer", "text": "No exactamente. La TRM es la referencia oficial. Bancos y plataformas compran tus dólares con su propia tasa, normalmente por debajo de la TRM, y pueden cobrar comisión." } }, { "@type": "Question", "name": "¿Qué TRM uso para calcular mi planilla si me pagan en dólares?", "acceptedAnswer": { "@type": "Answer", "text": "Cotizas sobre el valor en pesos que recibiste. Para estimarlo, usa la TRM del día del pago y la calculadora de aportes." } }, { "@type": "Question", "name": "¿Necesito una cuenta en dólares para recibir pagos del exterior?", "acceptedAnswer": { "@type": "Answer", "text": "No. Puedes recibirlos en tu cuenta en pesos, y el banco los convierte. Una cuenta en dólares te deja elegir cuándo cambiarlos. Compara opciones en cuenta en dólares en Colombia." } } ] } ] } | E10: Un solo script por página. Organization, WebSite y Person van en todas las páginas con el mismo @id. dateModified y lastReviewed = fecha real de la última edición (la misma visible en la página). FAQPage con las preguntas visibles del wireframe: si el texto cambia en el código, regenerar. La FAQ "¿A cómo está el dólar…" y el Dataset llevan valores dinámicos.
A11: P08 | B11: =URLs!C11 -> https://frilo.dev/guias/cuenta-en-dolares-colombia | C11: Article + FAQPage + BreadcrumbList | D11: { "@context": "https://schema.org", "@graph": [ { "@type": "Organization", "@id": "https://frilo.dev/#organization", "name": "Frilo", "url": "https://frilo.dev", "logo": "https://frilo.dev/logos/isotipo-oliva.png", "slogan": "Tus finanzas, mejor con Frilo", "areaServed": "CO" }, { "@type": "WebSite", "@id": "https://frilo.dev/#website", "url": "https://frilo.dev", "name": "Frilo", "inLanguage": "es-CO", "publisher": { "@id": "https://frilo.dev/#organization" } }, { "@type": "Person", "@id": "https://frilo.dev/#nicolas", "name": "Nicolás Suárez", "jobTitle": "Fundador de Frilo", "url": "https://frilo.dev/quienes-somos" }, { "@type": "WebPage", "@id": "https://frilo.dev/guias/cuenta-en-dolares-colombia", "url": "https://frilo.dev/guias/cuenta-en-dolares-colombia", "name": "Cuenta en dólares en Colombia: opciones, requisitos y costos", "description": "Compara las opciones para tener una cuenta en dólares en Colombia: requisitos, costos y tiempos de apertura. Guía para freelancers en 2026.", "inLanguage": "es-CO", "isPartOf": { "@id": "https://frilo.dev/#website" }, "dateModified": "2026-10-20", "reviewedBy": { "@type": "Organization", "name": "Equipo de finanzas Frilo", "parentOrganization": { "@id": "https://frilo.dev/#organization" } }, "lastReviewed": "2026-10-20", "mainEntity": { "@id": "https://frilo.dev/guias/cuenta-en-dolares-colombia#article" } }, { "@type": "Article", "@id": "https://frilo.dev/guias/cuenta-en-dolares-colombia#article", "headline": "Cuenta en dólares en Colombia: opciones, requisitos y costos", "description": "Compara las opciones para tener una cuenta en dólares en Colombia: requisitos, costos y tiempos de apertura. Guía para freelancers en 2026.", "mainEntityOfPage": "https://frilo.dev/guias/cuenta-en-dolares-colombia", "inLanguage": "es-CO", "author": { "@id": "https://frilo.dev/#nicolas" }, "publisher": { "@id": "https://frilo.dev/#organization" }, "datePublished": "2026-10-20", "dateModified": "2026-10-20", "image": "https://frilo.dev/og/guias/cuenta-en-dolares-colombia.png" }, { "@type": "BreadcrumbList", "itemListElement": [ { "@type": "ListItem", "position": 1, "name": "Inicio", "item": "https://frilo.dev" }, { "@type": "ListItem", "position": 2, "name": "Guías", "item": "https://frilo.dev/guias" }, { "@type": "ListItem", "position": 3, "name": "Cuenta en dólares" } ] }, { "@type": "FAQPage", "@id": "https://frilo.dev/guias/cuenta-en-dolares-colombia#faq", "mainEntity": [ { "@type": "Question", "name": "¿Un freelancer puede abrir una cuenta en dólares en Colombia?", "acceptedAnswer": { "@type": "Answer", "text": "Sí. Puedes abrirla en un banco con filial en el exterior o usar una plataforma digital. Revisa si la entidad está vigilada por la Superintendencia Financiera: algunas plataformas, como Littio, no lo están y no tienen el respaldo de Fogafín." } }, { "@type": "Question", "name": "¿Tengo que declarar una cuenta en dólares?", "acceptedAnswer": { "@type": "Answer", "text": "Los saldos y los ingresos en dólares se incluyen en tu declaración de renta. En lo cambiario, la DIAN explica que las operaciones de canalización obligatoria se hacen por intermediarios del mercado cambiario o por cuentas de compensación registradas en el Banco de la República, con declaración de cambio, y que debes guardar los soportes por cinco años. Revisa tu caso en la página de control cambiario de la DIAN." } }, { "@type": "Question", "name": "¿Cuánto cobran por recibir una transferencia en dólares?", "acceptedAnswer": { "@type": "Answer", "text": "Depende de la entidad. Por ejemplo, Littio cobra USD 2,99 por recibir desde EE. UU. o Europa (consultado el 20 de octubre de 2026). Además, al pasar a pesos se aplica la tasa de la entidad, no la TRM." } } ] } ] } | E11: Un solo script por página. Organization, WebSite y Person van en todas las páginas con el mismo @id. dateModified y lastReviewed = fecha real de la última edición (la misma visible en la página). FAQPage con las preguntas visibles del wireframe: si el texto cambia en el código, regenerar.
A12: P09 | B12: =URLs!C12 -> https://frilo.dev/guias/recibir-pagos-en-dolares-colombia | C12: Article + FAQPage + BreadcrumbList | D12: { "@context": "https://schema.org", "@graph": [ { "@type": "Organization", "@id": "https://frilo.dev/#organization", "name": "Frilo", "url": "https://frilo.dev", "logo": "https://frilo.dev/logos/isotipo-oliva.png", "slogan": "Tus finanzas, mejor con Frilo", "areaServed": "CO" }, { "@type": "WebSite", "@id": "https://frilo.dev/#website", "url": "https://frilo.dev", "name": "Frilo", "inLanguage": "es-CO", "publisher": { "@id": "https://frilo.dev/#organization" } }, { "@type": "Person", "@id": "https://frilo.dev/#nicolas", "name": "Nicolás Suárez", "jobTitle": "Fundador de Frilo", "url": "https://frilo.dev/quienes-somos" }, { "@type": "WebPage", "@id": "https://frilo.dev/guias/recibir-pagos-en-dolares-colombia", "url": "https://frilo.dev/guias/recibir-pagos-en-dolares-colombia", "name": "Cómo recibir pagos del exterior en dólares en Colombia", "description": "Recibe pagos del exterior en dólares en Colombia: opciones, costos, tiempos y qué debes declarar. Guía para freelancers e independientes.", "inLanguage": "es-CO", "isPartOf": { "@id": "https://frilo.dev/#website" }, "dateModified": "2026-10-20", "reviewedBy": { "@type": "Organization", "name": "Equipo de finanzas Frilo", "parentOrganization": { "@id": "https://frilo.dev/#organization" } }, "lastReviewed": "2026-10-20", "mainEntity": { "@id": "https://frilo.dev/guias/recibir-pagos-en-dolares-colombia#article" } }, { "@type": "Article", "@id": "https://frilo.dev/guias/recibir-pagos-en-dolares-colombia#article", "headline": "Cómo recibir pagos del exterior en dólares en Colombia", "description": "Recibe pagos del exterior en dólares en Colombia: opciones, costos, tiempos y qué debes declarar. Guía para freelancers e independientes.", "mainEntityOfPage": "https://frilo.dev/guias/recibir-pagos-en-dolares-colombia", "inLanguage": "es-CO", "author": { "@id": "https://frilo.dev/#nicolas" }, "publisher": { "@id": "https://frilo.dev/#organization" }, "datePublished": "2026-10-20", "dateModified": "2026-10-20", "image": "https://frilo.dev/og/guias/recibir-pagos-en-dolares-colombia.png" }, { "@type": "BreadcrumbList", "itemListElement": [ { "@type": "ListItem", "position": 1, "name": "Inicio", "item": "https://frilo.dev" }, { "@type": "ListItem", "position": 2, "name": "Guías", "item": "https://frilo.dev/guias" }, { "@type": "ListItem", "position": 3, "name": "Recibir pagos en dólares" } ] }, { "@type": "FAQPage", "@id": "https://frilo.dev/guias/recibir-pagos-en-dolares-colombia#faq", "mainEntity": [ { "@type": "Question", "name": "¿Puedo recibir dólares en una cuenta en pesos?", "acceptedAnswer": { "@type": "Answer", "text": "Sí. El banco recibe la transferencia y la convierte a pesos con su propia tasa, que suele ser menor que la TRM. Compara esa tasa y la comisión antes de elegir." } }, { "@type": "Question", "name": "¿Qué TRM se usa para calcular la planilla?", "acceptedAnswer": { "@type": "Answer", "text": "Cotizas sobre el valor en pesos de lo que recibiste. Para estimarlo, usa la TRM del día del pago y luego la calculadora de aportes." } }, { "@type": "Question", "name": "¿Tengo que pagar impuestos por recibir dólares?", "acceptedAnswer": { "@type": "Answer", "text": "Los pagos del exterior son ingresos y cuentan para tu declaración de renta como cualquier otro ingreso. Para las obligaciones cambiarias, consulta la página de control cambiario de la DIAN." } } ] } ] } | E12: Un solo script por página. Organization, WebSite y Person van en todas las páginas con el mismo @id. dateModified y lastReviewed = fecha real de la última edición (la misma visible en la página). FAQPage con las preguntas visibles del wireframe: si el texto cambia en el código, regenerar.
A13: P10 | B13: =URLs!C13 -> https://frilo.dev/calculadoras/interes-compuesto | C13: WebPage + WebApplication + FAQPage + BreadcrumbList | D13: { "@context": "https://schema.org", "@graph": [ { "@type": "Organization", "@id": "https://frilo.dev/#organization", "name": "Frilo", "url": "https://frilo.dev", "logo": "https://frilo.dev/logos/isotipo-oliva.png", "slogan": "Tus finanzas, mejor con Frilo", "areaServed": "CO" }, { "@type": "WebSite", "@id": "https://frilo.dev/#website", "url": "https://frilo.dev", "name": "Frilo", "inLanguage": "es-CO", "publisher": { "@id": "https://frilo.dev/#organization" } }, { "@type": "Person", "@id": "https://frilo.dev/#nicolas", "name": "Nicolás Suárez", "jobTitle": "Fundador de Frilo", "url": "https://frilo.dev/quienes-somos" }, { "@type": "WebPage", "@id": "https://frilo.dev/calculadoras/interes-compuesto", "url": "https://frilo.dev/calculadoras/interes-compuesto", "name": "Calculadora de interés compuesto: simula cuánto rinde tu ahorro", "description": "Simula cuánto crece tu ahorro con interés compuesto: monto inicial, aporte mensual, tasa efectiva anual y plazo. Gratis y sin registro.", "inLanguage": "es-CO", "isPartOf": { "@id": "https://frilo.dev/#website" }, "dateModified": "2026-10-20", "mainEntity": { "@id": "https://frilo.dev/calculadoras/interes-compuesto#app" }, "author": { "@id": "https://frilo.dev/#nicolas" }, "reviewedBy": { "@type": "Organization", "name": "Equipo de finanzas Frilo", "parentOrganization": { "@id": "https://frilo.dev/#organization" } }, "lastReviewed": "2026-10-20" }, { "@type": "WebApplication", "@id": "https://frilo.dev/calculadoras/interes-compuesto#app", "name": "Calculadora de interés compuesto: simula cuánto rinde tu ahorro", "url": "https://frilo.dev/calculadoras/interes-compuesto", "applicationCategory": "FinanceApplication", "operatingSystem": "Web", "inLanguage": "es-CO", "isAccessibleForFree": true, "offers": { "@type": "Offer", "price": "0", "priceCurrency": "COP" }, "publisher": { "@id": "https://frilo.dev/#organization" }, "dateModified": "2026-10-20" }, { "@type": "BreadcrumbList", "itemListElement": [ { "@type": "ListItem", "position": 1, "name": "Inicio", "item": "https://frilo.dev" }, { "@type": "ListItem", "position": 2, "name": "Calculadoras", "item": "https://frilo.dev/calculadoras" }, { "@type": "ListItem", "position": 3, "name": "Interés compuesto" } ] }, { "@type": "FAQPage", "@id": "https://frilo.dev/calculadoras/interes-compuesto#faq", "mainEntity": [ { "@type": "Question", "name": "¿Qué diferencia hay entre tasa E.A. y tasa nominal?", "acceptedAnswer": { "@type": "Answer", "text": "La tasa efectiva anual (E.A.) ya incluye el efecto de capitalizar los intereses. La nominal no: hay que convertirla según cuántas veces al año se capitaliza. Un 9% nominal con capitalización mensual equivale a cerca de 9,38% E.A." } }, { "@type": "Question", "name": "¿El 4x1000 afecta lo que rinde mi ahorro?", "acceptedAnswer": { "@type": "Answer", "text": "El 4x1000 (GMF) se cobra cuando retiras o transfieres dinero, no sobre los intereses. Puedes marcar una sola cuenta como exenta, con un tope mensual que define cada entidad según la ley (por ejemplo, Nu informa hasta $16 millones al mes)." } }, { "@type": "Question", "name": "¿Los rendimientos de una cuenta de ahorros pagan retención en la fuente?", "acceptedAnswer": { "@type": "Answer", "text": "Sí. En 2026 la retención en la fuente sobre intereses o rendimientos financieros es del 7%, sin base mínima (tabla de retención 2026). Activa la opción en la calculadora para verla descontada." } }, { "@type": "Question", "name": "¿Es mejor capitalización diaria o mensual?", "acceptedAnswer": { "@type": "Answer", "text": "Si la tasa que te dan es efectiva anual (E.A.), da igual: la capitalización ya está incluida. Solo importa cuando la tasa es nominal; ahí, entre más frecuente la capitalización, más rinde." } }, { "@type": "Question", "name": "¿Qué es la regla del 72?", "acceptedAnswer": { "@type": "Answer", "text": "Un atajo para estimar en cuántos años se duplica tu dinero: divide 72 entre la tasa anual. Al 9% E.A. tu ahorro se duplica en unos 8 años." } }, { "@type": "Question", "name": "¿Esta calculadora sirve para inversiones o solo para ahorro?", "acceptedAnswer": { "@type": "Answer", "text": "Sirve para cualquier tasa que se mantenga fija. En inversiones como fondos o acciones la rentabilidad no está garantizada y puede ser negativa. No es asesoría financiera." } } ] } ] } | E13: Un solo script por página. Organization, WebSite y Person van en todas las páginas con el mismo @id. dateModified y lastReviewed = fecha real de la última edición (la misma visible en la página). FAQPage con las preguntas visibles del wireframe: si el texto cambia en el código, regenerar.
... A24: APP | B24: =URLs!C24 -> https://app.frilo.dev | C24: Ninguno | D24: (sin datos estructurados) | E24: Sin schema.

Sheet Forecast base
A1: ID | B1: URL final | C1: Keyword objetivo | D1: Volumen keyword objetivo | E1: Volumen del grupo | F1: Clics/mes posición 10 | G1: Clics/mes posición 3 | H1: Clics/mes posición 1 | I1: Nota
A2: =URLs!A2 -> Home | B2: =URLs!C2 -> https://frilo.dev/ | C2: =URLs!L2 -> frilo | D2: =URLs!N2 -> s/d | E2: =URLs!P2 -> 0 | F2: =ROUND(E2*Supuestos!$B$4,0) -> 0 | G2: =ROUND(E2*Supuestos!$B$3,0) -> 0 | H2: =ROUND(E2*Supuestos!$B$2,0) -> 0 | I2: Sin volumen medido: completar con Ranki.
A3: =URLs!A3 -> Hub-C | B3: =URLs!C3 -> https://frilo.dev/calculadoras | C3: =URLs!L3 -> calculadoras para independientes | D3: =URLs!N3 -> s/d | E3: =URLs!P3 -> 0 | F3: =ROUND(E3*Supuestos!$B$4,0) -> 0 | G3: =ROUND(E3*Supuestos!$B$3,0) -> 0 | H3: =ROUND(E3*Supuestos!$B$2,0) -> 0 | I3: Sin volumen medido: completar con Ranki.
A4: =URLs!A4 -> P01 | B4: =URLs!C4 -> https://frilo.dev/calculadoras/aportes-independientes | C4: =URLs!L4 -> calculadora de aportes | D4: =URLs!N4 -> 2400 | E4: =URLs!P4 -> 2580 | F4: =ROUND(E4*Supuestos!$B$4,0) -> 41 | G4: =ROUND(E4*Supuestos!$B$3,0) -> 263 | H4: =ROUND(E4*Supuestos!$B$2,0) -> 1027
A5: =URLs!A5 -> P02 | B5: =URLs!C5 -> https://frilo.dev/guias/ibc-independientes | C5: =URLs!L5 -> ibc para independientes | D5: =URLs!N5 -> 90 | E5: =URLs!P5 -> 340 | F5: =ROUND(E5*Supuestos!$B$4,0) -> 5 | G5: =ROUND(E5*Supuestos!$B$3,0) -> 35 | H5: =ROUND(E5*Supuestos!$B$2,0) -> 135
A6: =URLs!A6 -> P03 | B6: =URLs!C6 -> https://frilo.dev/calculadoras/cesantias | C6: =URLs!L6 -> calculadora de intereses de cesantías | D6: =URLs!N6 -> 880 | E6: =URLs!P6 -> 1130 | F6: =ROUND(E6*Supuestos!$B$4,0) -> 18 | G6: =ROUND(E6*Supuestos!$B$3,0) -> 115 | H6: =ROUND(E6*Supuestos!$B$2,0) -> 450
A7: =URLs!A7 -> P04 | B7: =URLs!C7 -> https://frilo.dev/guias/descargar-planilla-seguridad-social | C7: =URLs!L7 -> descargar planilla de seguridad social | D7: =URLs!N7 -> 1300 | E7: =URLs!P7 -> 2110 | F7: =ROUND(E7*Supuestos!$B$4,0) -> 34 | G7: =ROUND(E7*Supuestos!$B$3,0) -> 215 | H7: =ROUND(E7*Supuestos!$B$2,0) -> 840
A8: =URLs!A8 -> P05 | B8: =URLs!C8 -> https://frilo.dev/calculadoras/fecha-pago-planilla | C8: =URLs!L8 -> fecha de pago planilla seguridad social | D8: =URLs!N8 -> 320 | E8: =URLs!P8 -> 320 | F8: =ROUND(E8*Supuestos!$B$4,0) -> 5 | G8: =ROUND(E8*Supuestos!$B$3,0) -> 33 | H8: =ROUND(E8*Supuestos!$B$2,0) -> 127
A9: =URLs!A9 -> P06 | B9: =URLs!C9 -> https://frilo.dev/glosario/sln | C9: =URLs!L9 -> sln en planilla de seguridad social | D9: =URLs!N9 -> 210 | E9: =URLs!P9 -> 210 | F9: =ROUND(E9*Supuestos!$B$4,0) -> 3 | G9: =ROUND(E9*Supuestos!$B$3,0) -> 21 | H9: =ROUND(E9*Supuestos!$B$2,0) -> 84
A10: =URLs!A10 -> P07 | B10: =URLs!C10 -> https://frilo.dev/dolar-hoy | C10: =URLs!L10 -> dolar hoy colombia | D10: =URLs!N10 -> 1000000 | E10: =URLs!P10 -> 3093600 | F10: =ROUND(E10*Supuestos!$B$4,0) -> 49498 | G10: =ROUND(E10*Supuestos!$B$3,0) -> 315547 | H10: =ROUND(E10*Supuestos!$B$2,0) -> 1231253 | I10: Techo: el conversor de Google se queda con buena parte de los clics.
A11: =URLs!A11 -> P08 | B11: =URLs!C11 -> https://frilo.dev/guias/cuenta-en-dolares-colombia | C11: =URLs!L11 -> cuenta en dolares en colombia | D11: =URLs!N11 -> 320 | E11: =URLs!P11 -> 1050 | F11: =ROUND(E11*Supuestos!$B$4,0) -> 17 | G11: =ROUND(E11*Supuestos!$B$3,0) -> 107 | H11: =ROUND(E11*Supuestos!$B$2,0) -> 418
A12: =URLs!A12 -> P09 | B12: =URLs!C12 -> https://frilo.dev/guias/recibir-pagos-en-dolares-colombia | C12: =URLs!L12 -> como recibir pagos en dolares en colombia | D12: =URLs!N12 -> 10 | E12: =URLs!P12 -> 10 | F12: =ROUND(E12*Supuestos!$B$4,0) -> 0 | G12: =ROUND(E12*Supuestos!$B$3,0) -> 1 | H12: =ROUND(E12*Supuestos!$B$2,0) -> 4
A13: =URLs!A13 -> P10 | B13: =URLs!C13 -> https://frilo.dev/calculadoras/interes-compuesto | C13: =URLs!L13 -> calculadora interés compuesto | D13: =URLs!N13 -> 5400 | E13: =URLs!P13 -> 5500 | F13: =ROUND(E13*Supuestos!$B$4,0) -> 88 | G13: =ROUND(E13*Supuestos!$B$3,0) -> 561 | H13: =ROUND(E13*Supuestos!$B$2,0) -> 2189
A14: =URLs!A14 -> P11 | B14: =URLs!C14 -> https://frilo.dev/guias/cuentas-de-ahorro-alto-rendimiento | C14: =URLs!L14 -> cuentas de ahorro de alto rendimiento | D14: =URLs!N14 -> 880 | E14: =URLs!P14 -> 1730 | F14: =ROUND(E14*Supuestos!$B$4,0) -> 28 | G14: =ROUND(E14*Supuestos!$B$3,0) -> 176 | H14: =ROUND(E14*Supuestos!$B$2,0) -> 689
A15: =URLs!A15 -> P12 | B15: =URLs!C15 -> https://frilo.dev/guias/cesantias-independientes | C15: =URLs!L15 -> cesantías para independientes | D15: =URLs!N15 -> s/d | E15: =URLs!P15 -> 0 | F15: =ROUND(E15*Supuestos!$B$4,0) -> 0 | G15: =ROUND(E15*Supuestos!$B$3,0) -> 0 | H15: =ROUND(E15*Supuestos!$B$2,0) -> 0 | I15: Sin volumen medido: completar con Ranki.
A16: =URLs!A16 -> Hub-G | B16: =URLs!C16 -> https://frilo.dev/guias | C16: =URLs!L16 -> guías para independientes | D16: =URLs!N16 -> s/d | E16: =URLs!P16 -> 0 | F16: =ROUND(E16*Supuestos!$B$4,0) -> 0 | G16: =ROUND(E16*Supuestos!$B$3,0) -> 0 | H16: =ROUND(E16*Supuestos!$B$2,0) -> 0 | I16: Sin volumen medido: completar con Ranki.
A17: =URLs!A17 -> Hub-Glo | B17: =URLs!C17 -> https://frilo.dev/glosario | C17: =URLs!L17 -> glosario seguridad social | D17: =URLs!N17 -> s/d | E17: =URLs!P17 -> 0 | F17: =ROUND(E17*Supuestos!$B$4,0) -> 0 | G17: =ROUND(E17*Supuestos!$B$3,0) -> 0 | H17: =ROUND(E17*Supuestos!$B$2,0) -> 0 | I17: Sin volumen medido: completar con Ranki.
C18: Total | E18: =SUM(E2:E17) -> 3108580 | F18: =SUM(F2:F17) -> 49737 | G18: =SUM(G2:G17) -> 317074 | H18: =SUM(H2:H17) -> 1237216
C19: Total sin P07 (dólar hoy) | E19: =E18-SUMIFS(E2:E17,A2:A17,"P07") -> 14980 | F19: =F18-SUMIFS(F2:F17,A2:A17,"P07") -> 239 | G19: =G18-SUMIFS(G2:G17,A2:A17,"P07") -> 1527 | H19: =H18-SUMIFS(H2:H17,A2:A17,"P07") -> 5963
A21: Clics = volumen del grupo × CTR de la hoja Supuestos. Estacionalidad: "calculadora de aportes" llega a 2x en enero (4.400 vs. 2.192 de promedio). Para un forecast mensual, multiplicar P01, P02, P03 y P05 por el índice de la hoja Estacionalidad del research.

Sheet Seguimiento
A1: ID | B1: URL final | C1: Keyword objetivo | D1: Fecha de publicación | E1: ¿Indexada? (Sí/No) | F1: Fecha de indexación | G1: Posición actual (keyword objetivo) | H1: Clics (28 días) | I1: Impresiones (28 días) | J1: CTR | K1: LCP (s) | L1: INP (ms) | M1: CLS | N1: Core Web Vitals | O1: Última revisión | P1: Comentarios
A2: =URLs!A2 -> Home | B2: =URLs!C2 -> https://frilo.dev/ | C2: =URLs!L2 -> frilo | D2: 46329 | E2: Sí | F2: 46331 | G2: 18 | H2: 42 | I2: 1350 | J2: =IF(OR(I2="",I2=0),"",H2/I2) -> 0.031111111 | K2: 2.1 | L2: 150 | M2: 0.04 | N2: =IF(OR(K2="",L2="",M2=""),"",IF(AND(K2<=2.5,L2<=200,M2<=0.1),"Bueno",IF(OR(K2>4,L2>500,M2>0.25),"Malo","Mejorable"))) -> Bueno | O2: 46357 | P2: FILA DE EJEMPLO: reemplazar con datos reales
A3: =URLs!A3 -> Hub-C | B3: =URLs!C3 -> https://frilo.dev/calculadoras | C3: =URLs!L3 -> calculadoras para independientes | J3: =IF(OR(I3="",I3=0),"",H3/I3) | N3: =IF(OR(K3="",L3="",M3=""),"",IF(AND(K3<=2.5,L3<=200,M3<=0.1),"Bueno",IF(OR(K3>4,L3>500,M3>0.25),"Malo","Mejorable")))
A4: =URLs!A4 -> P01 | B4: =URLs!C4 -> https://frilo.dev/calculadoras/aportes-independientes | C4: =URLs!L4 -> calculadora de aportes | J4: =IF(OR(I4="",I4=0),"",H4/I4) | N4: =IF(OR(K4="",L4="",M4=""),"",IF(AND(K4<=2.5,L4<=200,M4<=0.1),"Bueno",IF(OR(K4>4,L4>500,M4>0.25),"Malo","Mejorable")))
A5: =URLs!A5 -> P02 | B5: =URLs!C5 -> https://frilo.dev/guias/ibc-independientes | C5: =URLs!L5 -> ibc para independientes | J5: =IF(OR(I5="",I5=0),"",H5/I5) | N5: =IF(OR(K5="",L5="",M5=""),"",IF(AND(K5<=2.5,L5<=200,M5<=0.1),"Bueno",IF(OR(K5>4,L5>500,M5>0.25),"Malo","Mejorable")))
A6: =URLs!A6 -> P03 | B6: =URLs!C6 -> https://frilo.dev/calculadoras/cesantias | C6: =URLs!L6 -> calculadora de intereses de cesantías | J6: =IF(OR(I6="",I6=0),"",H6/I6) | N6: =IF(OR(K6="",L6="",M6=""),"",IF(AND(K6<=2.5,L6<=200,M6<=0.1),"Bueno",IF(OR(K6>4,L6>500,M6>0.25),"Malo","Mejorable")))
A7: =URLs!A7 -> P04 | B7: =URLs!C7 -> https://frilo.dev/guias/descargar-planilla-seguridad-social | C7: =URLs!L7 -> descargar planilla de seguridad social | J7: =IF(OR(I7="",I7=0),"",H7/I7) | N7: =IF(OR(K7="",L7="",M7=""),"",IF(AND(K7<=2.5,L7<=200,M7<=0.1),"Bueno",IF(OR(K7>4,L7>500,M7>0.25),"Malo","Mejorable")))
A8: =URLs!A8 -> P05 | B8: =URLs!C8 -> https://frilo.dev/calculadoras/fecha-pago-planilla | C8: =URLs!L8 -> fecha de pago planilla seguridad social | J8: =IF(OR(I8="",I8=0),"",H8/I8) | N8: =IF(OR(K8="",L8="",M8=""),"",IF(AND(K8<=2.5,L8<=200,M8<=0.1),"Bueno",IF(OR(K8>4,L8>500,M8>0.25),"Malo","Mejorable")))
A9: =URLs!A9 -> P06 | B9: =URLs!C9 -> https://frilo.dev/glosario/sln | C9: =URLs!L9 -> sln en planilla de seguridad social | J9: =IF(OR(I9="",I9=0),"",H9/I9) | N9: =IF(OR(K9="",L9="",M9=""),"",IF(AND(K9<=2.5,L9<=200,M9<=0.1),"Bueno",IF(OR(K9>4,L9>500,M9>0.25),"Malo","Mejorable")))
A10: =URLs!A10 -> P07 | B10: =URLs!C10 -> https://frilo.dev/dolar-hoy | C10: =URLs!L10 -> dolar hoy colombia | J10: =IF(OR(I10="",I10=0),"",H10/I10) | N10: =IF(OR(K10="",L10="",M10=""),"",IF(AND(K10<=2.5,L10<=200,M10<=0.1),"Bueno",IF(OR(K10>4,L10>500,M10>0.25),"Malo","Mejorable")))
A11: =URLs!A11 -> P08 | B11: =URLs!C11 -> https://frilo.dev/guias/cuenta-en-dolares-colombia | C11: =URLs!L11 -> cuenta en dolares en colombia | J11: =IF(OR(I11="",I11=0),"",H11/I11) | N11: =IF(OR(K11="",L11="",M11=""),"",IF(AND(K11<=2.5,L11<=200,M11<=0.1),"Bueno",IF(OR(K11>4,L11>500,M11>0.25),"Malo","Mejorable")))
A12: =URLs!A12 -> P09 | B12: =URLs!C12 -> https://frilo.dev/guias/recibir-pagos-en-dolares-colombia | C12: =URLs!L12 -> como recibir pagos en dolares en colombia | J12: =IF(OR(I12="",I12=0),"",H12/I12) | N12: =IF(OR(K12="",L12="",M12=""),"",IF(AND(K12<=2.5,L12<=200,M12<=0.1),"Bueno",IF(OR(K12>4,L12>500,M12>0.25),"Malo","Mejorable")))
A13: =URLs!A13 -> P10 | B13: =URLs!C13 -> https://frilo.dev/calculadoras/interes-compuesto | C13: =URLs!L13 -> calculadora interés compuesto | J13: =IF(OR(I13="",I13=0),"",H13/I13) | N13: =IF(OR(K13="",L13="",M13=""),"",IF(AND(K13<=2.5,L13<=200,M13<=0.1),"Bueno",IF(OR(K13>4,L13>500,M13>0.25),"Malo","Mejorable")))
A14: =URLs!A14 -> P11 | B14: =URLs!C14 -> https://frilo.dev/guias/cuentas-de-ahorro-alto-rendimiento | C14: =URLs!L14 -> cuentas de ahorro de alto rendimiento | J14: =IF(OR(I14="",I14=0),"",H14/I14) | N14: =IF(OR(K14="",L14="",M14=""),"",IF(AND(K14<=2.5,L14<=200,M14<=0.1),"Bueno",IF(OR(K14>4,L14>500,M14>0.25),"Malo","Mejorable")))
... A22: =URLs!A22 -> Legal-2 | B22: =URLs!C22 -> https://frilo.dev/politica-de-datos | C22: =URLs!L22 -> No aplica | J22: =IF(OR(I22="",I22=0),"",H22/I22) | N22: =IF(OR(K22="",L22="",M22=""),"",IF(AND(K22<=2.5,L22<=200,M22<=0.1),"Bueno",IF(OR(K22>4,L22>500,M22>0.25),"Malo","Mejorable")))
A24: Llenar las celdas amarillas con Search Console (indexación, clics, impresiones), Ranki (posición) y PageSpeed Insights o CrUX (LCP, INP, CLS). Umbrales "Bueno": LCP ≤ 2,5 s, INP ≤ 200 ms, CLS ≤ 0,1 (Google, web.dev/vitals). La fila 2 es un ejemplo de formato.

Sheet App y ambientes
A1: Dónde vive cada cosa
A3: Recomendación de URL para la app web
A4: Opción | B4: Cómo queda | C4: Evaluación
A5: Recomendada: subdominio | B5: Sitio en https://frilo.dev · App en https://app.frilo.dev | C5: La app no se indexa (noindex, nofollow), así que el subdominio no le quita autoridad SEO al sitio. Separa el JavaScript de la app del sitio: las páginas de contenido cargan solo lo suyo y su Core Web Vitals no depende de la app. Se despliegan por separado (un error en la app no tumba el sitio). Encaja con el brief §2.9, que ya define la cookie de sesión en el dominio .frilo.dev para compartir el registro entre sitio y app. Es la convención de los productos financieros que revisamos.
A6: Alternativa: subcarpeta | B6: Sitio en https://frilo.dev · App en https://frilo.dev/app | C6: Solo conviene si Claude Code ve que separar la app es costoso. Un solo proyecto y un solo despliegue, pero el sitio carga con la configuración de la app y cualquier cambio en la app redespliega el sitio. Requiere bloquear /app/ en robots.txt (ya está en la especificación) y noindex en todas sus rutas.
A8: Ambientes
A9: Ambiente | B9: URL | C9: Reglas
A10: Desarrollo local | B10: http://localhost:3000 (sitio) y el puerto actual de la app | C10: Datos de prueba. Nada se publica.
A11: Prueba (staging) del sitio | B11: URL de vista previa de Vercel del proyecto del sitio (rama de trabajo), opcionalmente con alias staging.frilo.dev | C11: Protegida con Vercel Authentication (Deployment Protection) para que solo la vean cuentas del equipo. Cabecera X-Robots-Tag: noindex, nofollow y robots.txt con "Disallow: /" en todo lo que no sea producción. Sin Google Analytics de producción.
A12: Prueba de la app | B12: URL de vista previa de Vercel del proyecto de la app | C12: Para probar el cambio de dominio, el registro embebido y el callback de Google antes de publicar. No tocar el dominio de producción.
A13: Producción | B13: https://frilo.dev (sitio) y https://app.frilo.dev (app) | C13: Solo cuando Nicolás escriba la instrucción de publicar. Hasta entonces frilo.dev sigue sirviendo la app como hoy.
A15: Redirecciones y cambios al publicar
A16: Origen | B16: Destino | C16: Nota
A17: frilo.dev/<rutas actuales de la app> (login, panel, ajustes, etc.) | B17: app.frilo.dev/<misma ruta> (301) | C17: Claude Code debe listar las rutas reales de la app antes de publicar. Ninguna debe chocar con las rutas del sitio (/calculadoras, /guias, /glosario, /dolar-hoy, /lp, /quienes-somos, /metodologia, /transparencia).
A18: Rutas actuales de Términos y Política de datos en la app | B18: frilo.dev/terminos y frilo.dev/politica-de-datos (301 si la ruta cambia) | C18: Las páginas legales pasan a servirse desde el sitio y la app enlaza a ellas.
A19: frilo.dev/<ruta>/ (con barra final) | B19: frilo.dev/<ruta> (301) | C19: Convención única sin barra final.
A20: /ahorro/cuentas-de-ahorro-rentables | B20: /guias/cuentas-de-ahorro-alto-rendimiento (301) | C20: Solo si llegó a publicarse.
A21: Supabase Auth: Site URL y Redirect URLs | B21: Agregar https://app.frilo.dev/** y https://frilo.dev/** (y las URL de vista previa durante las pruebas) | C21: Sin esto falla el inicio de sesión con código y con Google.
A22: Google Cloud: OAuth (orígenes y URI de redirección) | B22: Agregar app.frilo.dev y frilo.dev | C22: Mismo motivo.
A23: Correos de Resend y Vercel Cron | B23: Enlaces y endpoint /api/cron/recordatorios en app.frilo.dev | C23: El cron vive con la app.
A25: Archivos técnicos del sitio
A26: URL | B26: Contenido | C26: Nota
A27: https://frilo.dev/robots.txt | B27: User-agent: * · Disallow: /lp/ · Disallow: /app/ · Disallow: /api/ · Sitemap: https://frilo.dev/sitemap.xml | C27: No bloquear GPTBot, ClaudeBot, PerplexityBot ni Google-Extended. En staging: Disallow: /.
A28: https://frilo.dev/sitemap.xml | B28: Las URLs con "Sí" en la columna "En sitemap" de la hoja URLs | C28: lastmod = fecha real de la última edición del contenido, no la del build.
A29: https://frilo.dev/llms.txt | B29: Una línea por página clave: título, URL y qué responde | C29: Parte de la estrategia GEO.
A30: https://frilo.dev/og/<ruta>.png | B30: Imagen 1200×630 por página con la F y el H1 | C30: Generada con next/og.
A31: https://app.frilo.dev/robots.txt | B31: User-agent: * · Disallow: / | C31: Además de la cabecera X-Robots-Tag: noindex, nofollow.

Sheet Supuestos
A1: Supuesto | B1: Valor | C1: Fuente
A2: CTR posición 1 | B2: 0.398 | C2: First Page Sage, 'Google click-through rates by ranking position' (2026), tomado del Keyword research Frilo (v3), hoja Supuestos
A3: CTR posición 3 | B3: 0.102 | C3: First Page Sage, 'Google click-through rates by ranking position' (2026), tomado del Keyword research Frilo (v3), hoja Supuestos
A4: CTR posición 10 | B4: 0.016 | C4: First Page Sage, 'Google click-through rates by ranking position' (2026), tomado del Keyword research Frilo (v3), hoja Supuestos
A5: Nota | B5: Promedios para SERP sin elementos especiales. En P07 (dólar hoy) el conversor de Google reduce los clics reales: tomar esa cifra como techo.

Sheet Keywords
A1: Keyword | B1: Grupo temático | C1: ID página | D1: Rol en la página | E1: Intención | F1: Volumen/mes | G1: KD
A2: calculadora de aportes | B2: Aportes a seguridad social | C2: P01 | D2: Principal | E2: Transaccional | F2: 2400 | G2: 0
A3: calculadora de aportes para independientes y contratistas | B3: Aportes a seguridad social | C3: P01 | D3: Secundaria | E3: Transaccional | F3: 70
A4: calculadora de aportes 2026 | B4: Aportes a seguridad social | C4: P01 | D4: Secundaria | E4: Transaccional | F4: 40
A5: calculadora de liquidacion aportes en linea | B5: Aportes a seguridad social | C5: P01 | D5: Secundaria | E5: Transaccional | F5: 30
A6: calculadora de liquidacion planilla | B6: Aportes a seguridad social | C6: P01 | D6: Soporte (H2/FAQ) | E6: Transaccional | F6: 30
A7: calculadora de aportes como independiente | B7: Aportes a seguridad social | C7: P01 | D7: Soporte (H2/FAQ) | E7: Transaccional | F7: 10
A8: calculadora de liquidacion aportes | B8: Aportes a seguridad social | C8: P01 | D8: Soporte (H2/FAQ) | E8: Transaccional
A9: calculadora de aportes compensar | B9: Aportes a seguridad social | C9: P01 | D9: Marca de terceros | E9: Navegacional | F9: 170 | G9: 0
A10: calculadora de aportes mi planilla | B10: Aportes a seguridad social | C10: P01 | D10: Marca de terceros | E10: Navegacional | F10: 90
A11: calculadora de aportes pago simple | B11: Aportes a seguridad social | C11: P01 | D11: Marca de terceros | E11: Navegacional | F11: 30
A12: pago simple calculadora de aportes | B12: Aportes a seguridad social | C12: P01 | D12: Marca de terceros | E12: Navegacional | F12: 30
A13: calculadora de aportes soi | B13: Aportes a seguridad social | C13: P01 | D13: Marca de terceros | E13: Navegacional | F13: 10
A14: calculadora de aportes a seguridad social 2025 | B14: Aportes a seguridad social | C14: P01 | D14: Excluir | E14: Transaccional | F14: 20
A15: ibc para independientes | B15: IBC independientes | C15: P02 | D15: Principal | E15: Informativa | F15: 90 | G15: 0
A16: calculadora ibc independientes | B16: IBC independientes | C16: P02 | D16: Secundaria | E16: Transaccional | F16: 110
A17: como calcular el ibc para independientes 2026 | B17: IBC independientes | C17: P02 | D17: Secundaria | E17: Informativa | F17: 90
A18: como cambiar el ibc en soi para independientes | B18: IBC independientes | C18: P02 | D18: Soporte (H2/FAQ) | E18: Informativa | F18: 30
A19: ibc seguridad social independientes | B19: IBC independientes | C19: P02 | D19: Soporte (H2/FAQ) | E19: Informativa | F19: 20
A20: como calcular el ibc para independientes 2025 | B20: IBC independientes | C20: P02 | D20: Excluir | E20: Informativa | F20: 90
A21: calculadora de intereses de cesantías | B21: Cesantías | C21: P03 | D21: Principal | E21: Transaccional | F21: 880 | G21: 0
A22: intereses de cesantías 2026 calculadora | B22: Cesantías | C22: P03 | D22: Secundaria | E22: Transaccional | F22: 140
A23: calculadora de cesantías 2026 | B23: Cesantías | C23: P03 | D23: Secundaria | E23: Transaccional | F23: 70
A24: calculadora de cesantías colombia | B24: Cesantías | C24: P03 | D24: Soporte (H2/FAQ) | E24: Transaccional | F24: 20
A25: calculadora de cesantías e intereses | B25: Cesantías | C25: P03 | D25: Soporte (H2/FAQ) | E25: Transaccional | F25: 10
A26: calculadora de interes de cesantías | B26: Cesantías | C26: P03 | D26: Soporte (H2/FAQ) | E26: Transaccional | F26: 10
A27: calculadora sanción moratoria por no pago de cesantías | B27: Cesantías | C27: P03 | D27: Soporte (H2/FAQ) | E27: Informativa
A28: calculadora de cesantías porvenir | B28: Cesantías | C28: P03 | D28: Marca de terceros | E28: Navegacional | F28: 170 | G28: 0
A29: calculadora intereses de cesantías 2022 | B29: Cesantías | C29: P03 | D29: Excluir | E29: Transaccional | F29: 10 | G29: 0
A30: calculadora de cesantías 2024 | B30: Cesantías | C30: P03 | D30: Excluir | E30: Transaccional | F30: 10 | G30: 0
A31: intereses de cesantías 2023 calculadora | B31: Cesantías | C31: P03 | D31: Excluir | E31: Transaccional | F31: 10 | G31: 0
A32: calculadora intereses de cesantías 2025 colombia | B32: Cesantías | C32: P03 | D32: Excluir | E32: Transaccional | F32: 10
A33: intereses de cesantías 2021 calculadora | B33: Cesantías | C33: P03 | D33: Excluir | E33: Transaccional | F33: 10 | G33: 52
A34: calculadora de intereses de cesantías 2024 colombia | B34: Cesantías | C34: P03 | D34: Excluir | E34: Transaccional | F34: 10
A35: calculadora intereses de cesantías 2024 | B35: Cesantías | C35: P03 | D35: Excluir | E35: Transaccional | F35: 10 | G35: 0
A36: descargar planilla de seguridad social | B36: Planilla de seguridad social | C36: P04 | D36: Principal | E36: Informativa | F36: 1300 | G36: 0
A37: como descargar planilla de seguridad social | B37: Planilla de seguridad social | C37: P04 | D37: Secundaria | E37: Informativa | F37: 390 | G37: 1
A38: como verificar una planilla de seguridad social | B38: Planilla de seguridad social | C38: P04 | D38: Secundaria | E38: Informativa | F38: 210 | G38: 0
A39: planilla de seguridad social independiente | B39: Planilla de seguridad social | C39: P04 | D39: Secundaria | E39: Informativa | F39: 210 | G39: 0
A40: fecha de pago planilla seguridad social | B40: Planilla de seguridad social | C40: P05 | D40: Principal | E40: Informativa | F40: 320 | G40: 0
A41: sln en planilla de seguridad social | B41: Planilla de seguridad social | C41: P06 | D41: Principal | E41: Informativa | F41: 210 | G41: 0
A42: dolar hoy colombia | B42: Dólar hoy | C42: P07 | D42: Principal | E42: Informativa | F42: 1000000 | G42: 46
A43: precio dolar hoy colombia | B43: Dólar hoy | C43: P07 | D43: Secundaria | E43: Informativa | F43: 368000 | G43: 71
A44: precio del dolar colombiano hoy | B44: Dólar hoy | C44: P07 | D44: Secundaria | E44: Informativa | F44: 368000 | G44: 74
A45: valor del dolar hoy | B45: Dólar hoy | C45: P07 | D45: Secundaria | E45: Informativa | F45: 74000 | G45: 0
A46: valor del dolar hoy colombia | B46: Dólar hoy | C46: P07 | D46: Secundaria | E46: Informativa | F46: 40500 | G46: 49
... A57: abrir cuenta en dolares | B57: Cuenta en dólares | C57: P08 | D57: Soporte (H2/FAQ) | E57: Comercial | F57: 30 | G57: 55
A58: como abrir una cuenta en dolares | B58: Cuenta en dólares | C58: P08 | D58: Soporte (H2/FAQ) | E58: Informativa | F58: 30
A59: cuenta bancaria en dolares | B59: Cuenta en dólares | C59: P08 | D59: Soporte (H2/FAQ) | E59: Comercial | F59: 20
A60: cuenta bancaria en dolares en colombia | B60: Cuenta en dólares | C60: P08 | D60: Soporte (H2/FAQ) | E60: Comercial | F60: 20
A61: beneficios de cuenta en dolares | B61: Cuenta en dólares | C61: P08 | D61: Soporte (H2/FAQ) | E61: Informativa | F61: 10
A62: cuenta en dolares bancolombia | B62: Cuenta en dólares | C62: P08 | D62: Marca de terceros | E62: Navegacional | F62: 720 | G62: 0
A63: cuenta de ahorros en dolares bancolombia | B63: Cuenta en dólares | C63: P08 | D63: Marca de terceros | E63: Navegacional | F63: 40
A64: cuenta en dolares davivienda panama | B64: Cuenta en dólares | C64: P08 | D64: Marca de terceros | E64: Navegacional | F64: 40
A65: como recibir pagos en dolares en colombia | B65: Pagos en dólares | C65: P09 | D65: Principal | E65: Comercial | F65: 10
A66: calculadora interés compuesto | B66: Ahorro e interés compuesto | C66: P10 | D66: Principal | E66: Transaccional | F66: 5400
A67: simulador de ahorro | B67: Ahorro e interés compuesto | C67: P10 | D67: Secundaria | E67: Transaccional | F67: 50
A68: calculadora de ahorro | B68: Ahorro e interés compuesto | C68: P10 | D68: Secundaria | E68: Transaccional | F68: 50
A69: calcular intereses cuenta de ahorros | B69: Ahorro e interés compuesto | C69: P10 | D69: Soporte (H2/FAQ) | E69: Informativa
A70: cuentas de ahorro de alto rendimiento | B70: Cuentas de ahorro | C70: P11 | D70: Principal | E70: Comercial | F70: 880
A71: cuenta de ahorros sin cuota de manejo | B71: Cuentas de ahorro | C71: P11 | D71: Secundaria | E71: Comercial | F71: 480
A72: mejores cuentas de ahorro colombia | B72: Cuentas de ahorro | C72: P11 | D72: Secundaria | E72: Comercial | F72: 140
A73: cuentas de ahorro con mayor rentabilidad | B73: Cuentas de ahorro | C73: P11 | D73: Secundaria | E73: Comercial | F73: 110
A74: bancos digitales colombia | B74: Cuentas de ahorro | C74: P11 | D74: Secundaria | E74: Informativa | F74: 50
A75: cuenta de ahorro rentable | B75: Cuentas de ahorro | C75: P11 | D75: Soporte (H2/FAQ) | E75: Comercial | F75: 30
A76: neobancos colombia | B76: Cuentas de ahorro | C76: P11 | D76: Soporte (H2/FAQ) | E76: Informativa | F76: 30
A77: cdt o cuenta de ahorros | B77: Cuentas de ahorro | C77: P11 | D77: Soporte (H2/FAQ) | E77: Informativa | F77: 10
A78: cuenta de ahorro vs cdt | B78: Cuentas de ahorro | C78: P11 | D78: Soporte (H2/FAQ) | E78: Informativa
A79: cuentas de ahorro con mayor rentabilidad colombia | B79: Cuentas de ahorro | C79: P11 | D79: Soporte (H2/FAQ) | E79: Comercial
A80: cuenta de ahorros que más paga | B80: Cuentas de ahorro | C80: P11 | D80: Soporte (H2/FAQ) | E80: Comercial
A81: cuentas de ahorro que más pagan en colombia | B81: Cuentas de ahorro | C81: P11 | D81: Soporte (H2/FAQ) | E81: Comercial
A82: cuenta de ahorros con rentabilidad diaria | B82: Cuentas de ahorro | C82: P11 | D82: Soporte (H2/FAQ) | E82: Comercial
A83: bancos que más pagan por ahorrar | B83: Cuentas de ahorro | C83: P11 | D83: Soporte (H2/FAQ) | E83: Comercial
A84: cuenta de ahorros exenta de 4x1000 | B84: Cuentas de ahorro | C84: P11 | D84: Soporte (H2/FAQ) | E84: Comercial
A85: dónde ahorrar dinero en colombia | B85: Cuentas de ahorro | C85: P11 | D85: Soporte (H2/FAQ) | E85: Informativa
A86: dónde poner a rendir mi dinero | B86: Cuentas de ahorro | C86: P11 | D86: Soporte (H2/FAQ) | E86: Informativa
A87: bancos digitales están cubiertos por fogafín | B87: Cuentas de ahorro | C87: P11 | D87: Soporte (H2/FAQ) | E87: Informativa
A88: dónde ahorrar la prima | B88: Cuentas de ahorro | C88: P11 | D88: Soporte (H2/FAQ) | E88: Informativa
A89: qué hacer con la prima | B89: Cuentas de ahorro | C89: P11 | D89: Soporte (H2/FAQ) | E89: Informativa
A90: en qué invertir la prima | B90: Cuentas de ahorro | C90: P11 | D90: Soporte (H2/FAQ) | E90: Informativa
A91: lulo bank cuenta de ahorros | B91: Cuentas de ahorro | C91: P11 | D91: Marca de terceros | E91: Navegacional | F91: 260
A92: lulo bank es seguro | B92: Cuentas de ahorro | C92: P11 | D92: Marca de terceros | E92: Navegacional | F92: 70
A93: lulo bank tasa | B93: Cuentas de ahorro | C93: P11 | D93: Marca de terceros | E93: Navegacional | F93: 20
A94: lulo bank vs nu | B94: Cuentas de ahorro | C94: P11 | D94: Marca de terceros | E94: Navegacional | F94: 20
A95: nu colombia es seguro | B95: Cuentas de ahorro | C95: P11 | D95: Marca de terceros | E95: Navegacional | F95: 10
A96: rappipay es confiable | B96: Cuentas de ahorro | C96: P11 | D96: Marca de terceros | E96: Navegacional | F96: 10
A97: lulo bank rentabilidad | B97: Cuentas de ahorro | C97: P11 | D97: Marca de terceros | E97: Navegacional
A98: rappicuenta rentabilidad | B98: Cuentas de ahorro | C98: P11 | D98: Marca de terceros | E98: Navegacional
A99: rappipay tasa | B99: Cuentas de ahorro | C99: P11 | D99: Marca de terceros | E99: Navegacional
A100: cajitas nu tasa | B100: Cuentas de ahorro | C100: P11 | D100: Marca de terceros | E100: Navegacional
A101: nu colombia rentabilidad | B101: Cuentas de ahorro | C101: P11 | D101: Marca de terceros | E101: Navegacional
A102: nu vs rappipay | B102: Cuentas de ahorro | C102: P11 | D102: Marca de terceros | E102: Navegacional
A103: pibank tasa | B103: Cuentas de ahorro | C103: P11 | D103: Marca de terceros | E103: Navegacional
A104: ualá colombia rendimiento | B104: Cuentas de ahorro | C104: P11 | D104: Marca de terceros | E104: Navegacional
A105: global66 cuenta remunerada | B105: Cuentas de ahorro | C105: P11 | D105: Marca de terceros | E105: Navegacional
A106: dónde guardar las cesantías | B106: Prima y cesantías | C106: P12 | D106: Secundaria | E106: Informativa
A107: qué hacer con las cesantías | B107: Prima y cesantías | C107: P12 | D107: Secundaria | E107: Informativa
